{"document": [{"box": [54, 41, 100, 54], "text": "KOOL", "id": 0, "words": [{"box": [54, 41, 100, 54], "id": 0, "text": "K"}, {"box": [54, 41, 100, 54], "id": 1, "text": "O"}, {"box": [54, 41, 100, 54], "id": 2, "text": "O"}, {"box": [54, 41, 100, 54], "id": 3, "text": "L"}]}, {"box": [54, 107, 155, 126], "text": "DESCRIPTION:", "id": 1, "words": [{"box": [54, 107, 155, 126], "id": 5, "text": "D"}, {"box": [54, 107, 155, 126], "id": 6, "text": "E"}, {"box": [54, 107, 155, 126], "id": 7, "text": "S"}, {"box": [54, 107, 155, 126], "id": 8, "text": "C"}, {"box": [54, 107, 155, 126], "id": 9, "text": "R"}, {"box": [54, 107, 155, 126], "id": 10, "text": "I"}, {"box": [54, 107, 155, 126], "id": 11, "text": "P"}, {"box": [54, 107, 155, 126], "id": 12, "text": "T"}, {"box": [54, 107, 155, 126], "id": 13, "text": "I"}, {"box": [54, 107, 155, 126], "id": 14, "text": "O"}, {"box": [54, 107, 155, 126], "id": 15, "text": "N"}, {"box": [54, 107, 155, 126], "id": 16, "text": ":"}]}, {"box": [54, 224, 132, 238], "text": "SUPPLIER:", "id": 2, "words": [{"box": [54, 224, 132, 238], "id": 18, "text": "S"}, {"box": [54, 224, 132, 238], "id": 19, "text": "U"}, {"box": [54, 224, 132, 238], "id": 20, "text": "P"}, {"box": [54, 224, 132, 238], "id": 21, "text": "P"}, {"box": [54, 224, 132, 238], "id": 22, "text": "L"}, {"box": [54, 224, 132, 238], "id": 23, "text": "I"}, {"box": [54, 224, 132, 238], "id": 24, "text": "E"}, {"box": [54, 224, 132, 238], "id": 25, "text": "R"}, {"box": [54, 224, 132, 238], "id": 26, "text": ":"}]}, {"box": [553, 527, 637, 545], "text": "CUMULATIVE", "id": 3, "words": [{"box": [553, 527, 637, 545], "id": 28, "text": "C"}, {"box": [553, 527, 637, 545], "id": 29, "text": "U"}, {"box": [553, 527, 637, 545], "id": 30, "text": "M"}, {"box": [553, 527, 637, 545], "id": 31, "text": "U"}, {"box": [553, 527, 637, 545], "id": 32, "text": "L"}, {"box": [553, 527, 637, 545], "id": 33, "text": "A"}, {"box": [553, 527, 637, 545], "id": 34, "text": "T"}, {"box": [553, 527, 637, 545], "id": 35, "text": "I"}, {"box": [553, 527, 637, 545], "id": 36, "text": "V"}, {"box": [553, 527, 637, 545], "id": 37, "text": "E"}]}, {"box": [195, 568, 227, 583], "text": "JAN", "id": 4, "words": [{"box": [195, 568, 227, 583], "id": 39, "text": "J"}, {"box": [195, 568, 227, 583], "id": 40, "text": "A"}, {"box": [195, 568, 227, 583], "id": 41, "text": "N"}]}, {"box": [678, 950, 744, 968], "text": "466024372", "id": 5, "words": [{"box": [678, 950, 744, 968], "id": 43, "text": "4"}, {"box": [678, 950, 744, 968], "id": 44, "text": "6"}, {"box": [678, 950, 744, 968], "id": 45, "text": "6"}, {"box": [678, 950, 744, 968], "id": 46, "text": "0"}, {"box": [678, 950, 744, 968], "id": 47, "text": "2"}, {"box": [678, 950, 744, 968], "id": 48, "text": "4"}, {"box": [678, 950, 744, 968], "id": 49, "text": "3"}, {"box": [678, 950, 744, 968], "id": 50, "text": "7"}, {"box": [678, 950, 744, 968], "id": 51, "text": "2"}]}, {"box": [548, 884, 671, 906], "text": "466024372", "id": 6, "words": [{"box": [548, 884, 671, 906], "id": 53, "text": "4"}, {"box": [548, 884, 671, 906], "id": 54, "text": "6"}, {"box": [548, 884, 671, 906], "id": 55, "text": "6"}, {"box": [548, 884, 671, 906], "id": 56, "text": "0"}, {"box": [548, 884, 671, 906], "id": 57, "text": "2"}, {"box": [548, 884, 671, 906], "id": 58, "text": "4"}, {"box": [548, 884, 671, 906], "id": 59, "text": "3"}, {"box": [548, 884, 671, 906], "id": 60, "text": "7"}, {"box": [548, 884, 671, 906], "id": 61, "text": "2"}]}, {"box": [430, 35, 527, 55], "text": "PROJECT NO.", "id": 7, "words": [{"box": [430, 35, 496, 54], "id": 63, "text": "P"}, {"box": [430, 35, 496, 54], "id": 64, "text": "R"}, {"box": [430, 35, 496, 54], "id": 65, "text": "O"}, {"box": [430, 35, 496, 54], "id": 66, "text": "J"}, {"box": [430, 35, 496, 54], "id": 67, "text": "E"}, {"box": [430, 35, 496, 54], "id": 68, "text": "C"}, {"box": [430, 35, 496, 54], "id": 69, "text": "T"}, {"box": [430, 35, 496, 54], "id": 70, "text": " "}, {"box": [501, 38, 527, 55], "id": 71, "text": "N"}, {"box": [501, 38, 527, 55], "id": 72, "text": "O"}, {"box": [501, 38, 527, 55], "id": 73, "text": "."}]}, {"box": [558, 31, 653, 51], "text": "1987- 144- K", "id": 8, "words": [{"box": [558, 33, 600, 48], "id": 75, "text": "1"}, {"box": [558, 33, 600, 48], "id": 76, "text": "9"}, {"box": [558, 33, 600, 48], "id": 77, "text": "8"}, {"box": [558, 33, 600, 48], "id": 78, "text": "7"}, {"box": [558, 33, 600, 48], "id": 79, "text": "-"}, {"box": [558, 33, 600, 48], "id": 80, "text": " "}, {"box": [603, 34, 636, 51], "id": 81, "text": "1"}, {"box": [603, 34, 636, 51], "id": 82, "text": "4"}, {"box": [603, 34, 636, 51], "id": 83, "text": "4"}, {"box": [603, 34, 636, 51], "id": 84, "text": "-"}, {"box": [603, 34, 636, 51], "id": 85, "text": " "}, {"box": [634, 31, 653, 49], "id": 86, "text": "K"}]}, {"box": [58, 55, 193, 72], "text": "0595- 529- 1510 -0", "id": 9, "words": [{"box": [58, 58, 100, 69], "id": 88, "text": "0"}, {"box": [58, 58, 100, 69], "id": 89, "text": "5"}, {"box": [58, 58, 100, 69], "id": 90, "text": "9"}, {"box": [58, 58, 100, 69], "id": 91, "text": "5"}, {"box": [58, 58, 100, 69], "id": 92, "text": "-"}, {"box": [58, 58, 100, 69], "id": 93, "text": " "}, {"box": [103, 58, 134, 72], "id": 94, "text": "5"}, {"box": [103, 58, 134, 72], "id": 95, "text": "2"}, {"box": [103, 58, 134, 72], "id": 96, "text": "9"}, {"box": [103, 58, 134, 72], "id": 97, "text": "-"}, {"box": [103, 58, 134, 72], "id": 98, "text": " "}, {"box": [137, 55, 169, 72], "id": 99, "text": "1"}, {"box": [137, 55, 169, 72], "id": 100, "text": "5"}, {"box": [137, 55, 169, 72], "id": 101, "text": "1"}, {"box": [137, 55, 169, 72], "id": 102, "text": "0"}, {"box": [137, 55, 169, 72], "id": 103, "text": " "}, {"box": [171, 57, 193, 71], "id": 104, "text": "-"}, {"box": [171, 57, 193, 71], "id": 105, "text": "0"}]}, {"box": [197, 100, 625, 125], "text": "KMDP ANALYSIS UTILIZING BLACK SWITCHING STUDY DATA", "id": 10, "words": [{"box": [197, 107, 236, 124], "id": 107, "text": "K"}, {"box": [197, 107, 236, 124], "id": 108, "text": "M"}, {"box": [197, 107, 236, 124], "id": 109, "text": "D"}, {"box": [197, 107, 236, 124], "id": 110, "text": "P"}, {"box": [197, 107, 236, 124], "id": 111, "text": " "}, {"box": [245, 108, 315, 123], "id": 112, "text": "A"}, {"box": [245, 108, 315, 123], "id": 113, "text": "N"}, {"box": [245, 108, 315, 123], "id": 114, "text": "A"}, {"box": [245, 108, 315, 123], "id": 115, "text": "L"}, {"box": [245, 108, 315, 123], "id": 116, "text": "Y"}, {"box": [245, 108, 315, 123], "id": 117, "text": "S"}, {"box": [245, 108, 315, 123], "id": 118, "text": "I"}, {"box": [245, 108, 315, 123], "id": 119, "text": "S"}, {"box": [245, 108, 315, 123], "id": 120, "text": " "}, {"box": [322, 106, 400, 125], "id": 121, "text": "U"}, {"box": [322, 106, 400, 125], "id": 122, "text": "T"}, {"box": [322, 106, 400, 125], "id": 123, "text": "I"}, {"box": [322, 106, 400, 125], "id": 124, "text": "L"}, {"box": [322, 106, 400, 125], "id": 125, "text": "I"}, {"box": [322, 106, 400, 125], "id": 126, "text": "Z"}, {"box": [322, 106, 400, 125], "id": 127, "text": "I"}, {"box": [322, 106, 400, 125], "id": 128, "text": "N"}, {"box": [322, 106, 400, 125], "id": 129, "text": "G"}, {"box": [322, 106, 400, 125], "id": 130, "text": " "}, {"box": [403, 104, 444, 122], "id": 131, "text": "B"}, {"box": [403, 104, 444, 122], "id": 132, "text": "L"}, {"box": [403, 104, 444, 122], "id": 133, "text": "A"}, {"box": [403, 104, 444, 122], "id": 134, "text": "C"}, {"box": [403, 104, 444, 122], "id": 135, "text": "K"}, {"box": [403, 104, 444, 122], "id": 136, "text": " "}, {"box": [453, 100, 531, 121], "id": 137, "text": "S"}, {"box": [453, 100, 531, 121], "id": 138, "text": "W"}, {"box": [453, 100, 531, 121], "id": 139, "text": "I"}, {"box": [453, 100, 531, 121], "id": 140, "text": "T"}, {"box": [453, 100, 531, 121], "id": 141, "text": "C"}, {"box": [453, 100, 531, 121], "id": 142, "text": "H"}, {"box": [453, 100, 531, 121], "id": 143, "text": "I"}, {"box": [453, 100, 531, 121], "id": 144, "text": "N"}, {"box": [453, 100, 531, 121], "id": 145, "text": "G"}, {"box": [453, 100, 531, 121], "id": 146, "text": " "}, {"box": [538, 104, 583, 121], "id": 147, "text": "S"}, {"box": [538, 104, 583, 121], "id": 148, "text": "T"}, {"box": [538, 104, 583, 121], "id": 149, "text": "U"}, {"box": [538, 104, 583, 121], "id": 150, "text": "D"}, {"box": [538, 104, 583, 121], "id": 151, "text": "Y"}, {"box": [538, 104, 583, 121], "id": 152, "text": " "}, {"box": [587, 103, 625, 117], "id": 153, "text": "D"}, {"box": [587, 103, 625, 117], "id": 154, "text": "A"}, {"box": [587, 103, 625, 117], "id": 155, "text": "T"}, {"box": [587, 103, 625, 117], "id": 156, "text": "A"}]}, {"box": [200, 177, 278, 195], "text": "C. B. Pugh", "id": 11, "words": [{"box": [200, 177, 217, 192], "id": 158, "text": "C"}, {"box": [200, 177, 217, 192], "id": 159, "text": "."}, {"box": [200, 177, 217, 192], "id": 160, "text": " "}, {"box": [218, 178, 236, 192], "id": 161, "text": "B"}, {"box": [218, 178, 236, 192], "id": 162, "text": "."}, {"box": [218, 178, 236, 192], "id": 163, "text": " "}, {"box": [245, 180, 278, 195], "id": 164, "text": "P"}, {"box": [245, 180, 278, 195], "id": 165, "text": "u"}, {"box": [245, 180, 278, 195], "id": 166, "text": "g"}, {"box": [245, 180, 278, 195], "id": 167, "text": "h"}]}, {"box": [200, 218, 308, 235], "text": "Market Facts", "id": 12, "words": [{"box": [200, 221, 257, 235], "id": 169, "text": "M"}, {"box": [200, 221, 257, 235], "id": 170, "text": "a"}, {"box": [200, 221, 257, 235], "id": 171, "text": "r"}, {"box": [200, 221, 257, 235], "id": 172, "text": "k"}, {"box": [200, 221, 257, 235], "id": 173, "text": "e"}, {"box": [200, 221, 257, 235], "id": 174, "text": "t"}, {"box": [200, 221, 257, 235], "id": 175, "text": " "}, {"box": [261, 218, 308, 235], "id": 176, "text": "F"}, {"box": [261, 218, 308, 235], "id": 177, "text": "a"}, {"box": [261, 218, 308, 235], "id": 178, "text": "c"}, {"box": [261, 218, 308, 235], "id": 179, "text": "t"}, {"box": [261, 218, 308, 235], "id": 180, "text": "s"}]}, {"box": [198, 258, 372, 280], "text": "12, 500 (10- 15- 87)", "id": 13, "words": [{"box": [198, 262, 226, 280], "id": 182, "text": "1"}, {"box": [198, 262, 226, 280], "id": 183, "text": "2"}, {"box": [198, 262, 226, 280], "id": 184, "text": ","}, {"box": [198, 262, 226, 280], "id": 185, "text": " "}, {"box": [231, 262, 259, 279], "id": 186, "text": "5"}, {"box": [231, 262, 259, 279], "id": 187, "text": "0"}, {"box": [231, 262, 259, 279], "id": 188, "text": "0"}, {"box": [231, 262, 259, 279], "id": 189, "text": " "}, {"box": [283, 258, 323, 277], "id": 190, "text": "("}, {"box": [283, 258, 323, 277], "id": 191, "text": "1"}, {"box": [283, 258, 323, 277], "id": 192, "text": "0"}, {"box": [283, 258, 323, 277], "id": 193, "text": "-"}, {"box": [283, 258, 323, 277], "id": 194, "text": " "}, {"box": [322, 261, 344, 279], "id": 195, "text": "1"}, {"box": [322, 261, 344, 279], "id": 196, "text": "5"}, {"box": [322, 261, 344, 279], "id": 197, "text": "-"}, {"box": [322, 261, 344, 279], "id": 198, "text": " "}, {"box": [344, 262, 372, 276], "id": 199, "text": "8"}, {"box": [344, 262, 372, 276], "id": 200, "text": "7"}, {"box": [344, 262, 372, 276], "id": 201, "text": ")"}]}, {"box": [460, 275, 659, 296], "text": "CARRYOVER TO 1988 -- 0", "id": 14, "words": [{"box": [460, 277, 547, 296], "id": 203, "text": "C"}, {"box": [460, 277, 547, 296], "id": 204, "text": "A"}, {"box": [460, 277, 547, 296], "id": 205, "text": "R"}, {"box": [460, 277, 547, 296], "id": 206, "text": "R"}, {"box": [460, 277, 547, 296], "id": 207, "text": "Y"}, {"box": [460, 277, 547, 296], "id": 208, "text": "O"}, {"box": [460, 277, 547, 296], "id": 209, "text": "V"}, {"box": [460, 277, 547, 296], "id": 210, "text": "E"}, {"box": [460, 277, 547, 296], "id": 211, "text": "R"}, {"box": [460, 277, 547, 296], "id": 212, "text": " "}, {"box": [553, 276, 571, 294], "id": 213, "text": "T"}, {"box": [553, 276, 571, 294], "id": 214, "text": "O"}, {"box": [553, 276, 571, 294], "id": 215, "text": " "}, {"box": [577, 275, 608, 294], "id": 216, "text": "1"}, {"box": [577, 275, 608, 294], "id": 217, "text": "9"}, {"box": [577, 275, 608, 294], "id": 218, "text": "8"}, {"box": [577, 275, 608, 294], "id": 219, "text": "8"}, {"box": [577, 275, 608, 294], "id": 220, "text": " "}, {"box": [619, 277, 638, 292], "id": 221, "text": "-"}, {"box": [619, 277, 638, 292], "id": 222, "text": "-"}, {"box": [619, 277, 638, 292], "id": 223, "text": " "}, {"box": [639, 276, 659, 290], "id": 224, "text": "0"}]}, {"box": [55, 179, 165, 196], "text": "MR PERSONNEL:", "id": 15, "words": [{"box": [55, 179, 76, 196], "id": 226, "text": "M"}, {"box": [55, 179, 76, 196], "id": 227, "text": "R"}, {"box": [55, 179, 76, 196], "id": 228, "text": " "}, {"box": [81, 179, 165, 196], "id": 229, "text": "P"}, {"box": [81, 179, 165, 196], "id": 230, "text": "E"}, {"box": [81, 179, 165, 196], "id": 231, "text": "R"}, {"box": [81, 179, 165, 196], "id": 232, "text": "S"}, {"box": [81, 179, 165, 196], "id": 233, "text": "O"}, {"box": [81, 179, 165, 196], "id": 234, "text": "N"}, {"box": [81, 179, 165, 196], "id": 235, "text": "N"}, {"box": [81, 179, 165, 196], "id": 236, "text": "E"}, {"box": [81, 179, 165, 196], "id": 237, "text": "L"}, {"box": [81, 179, 165, 196], "id": 238, "text": ":"}]}, {"box": [55, 262, 194, 279], "text": "AUTHORIZED COST:", "id": 16, "words": [{"box": [55, 262, 141, 277], "id": 240, "text": "A"}, {"box": [55, 262, 141, 277], "id": 241, "text": "U"}, {"box": [55, 262, 141, 277], "id": 242, "text": "T"}, {"box": [55, 262, 141, 277], "id": 243, "text": "H"}, {"box": [55, 262, 141, 277], "id": 244, "text": "O"}, {"box": [55, 262, 141, 277], "id": 245, "text": "R"}, {"box": [55, 262, 141, 277], "id": 246, "text": "I"}, {"box": [55, 262, 141, 277], "id": 247, "text": "Z"}, {"box": [55, 262, 141, 277], "id": 248, "text": "E"}, {"box": [55, 262, 141, 277], "id": 249, "text": "D"}, {"box": [55, 262, 141, 277], "id": 250, "text": " "}, {"box": [146, 262, 194, 279], "id": 251, "text": "C"}, {"box": [146, 262, 194, 279], "id": 252, "text": "O"}, {"box": [146, 262, 194, 279], "id": 253, "text": "S"}, {"box": [146, 262, 194, 279], "id": 254, "text": "T"}, {"box": [146, 262, 194, 279], "id": 255, "text": ":"}]}, {"box": [75, 517, 151, 551], "text": "RELEASED TO ACCTG", "id": 17, "words": [{"box": [78, 517, 151, 530], "id": 257, "text": "R"}, {"box": [78, 517, 151, 530], "id": 258, "text": "E"}, {"box": [78, 517, 151, 530], "id": 259, "text": "L"}, {"box": [78, 517, 151, 530], "id": 260, "text": "E"}, {"box": [78, 517, 151, 530], "id": 261, "text": "A"}, {"box": [78, 517, 151, 530], "id": 262, "text": "S"}, {"box": [78, 517, 151, 530], "id": 263, "text": "E"}, {"box": [78, 517, 151, 530], "id": 264, "text": "D"}, {"box": [78, 517, 151, 530], "id": 265, "text": " "}, {"box": [75, 534, 100, 546], "id": 266, "text": "T"}, {"box": [75, 534, 100, 546], "id": 267, "text": "O"}, {"box": [75, 534, 100, 546], "id": 268, "text": " "}, {"box": [106, 534, 148, 551], "id": 269, "text": "A"}, {"box": [106, 534, 148, 551], "id": 270, "text": "C"}, {"box": [106, 534, 148, 551], "id": 271, "text": "C"}, {"box": [106, 534, 148, 551], "id": 272, "text": "T"}, {"box": [106, 534, 148, 551], "id": 273, "text": "G"}]}, {"box": [292, 509, 389, 548], "text": "PAID OUT OF 1987 BUDGET", "id": 18, "words": [{"box": [292, 514, 330, 528], "id": 275, "text": "P"}, {"box": [292, 514, 330, 528], "id": 276, "text": "A"}, {"box": [292, 514, 330, 528], "id": 277, "text": "I"}, {"box": [292, 514, 330, 528], "id": 278, "text": "D"}, {"box": [292, 514, 330, 528], "id": 279, "text": " "}, {"box": [334, 514, 360, 528], "id": 280, "text": "O"}, {"box": [334, 514, 360, 528], "id": 281, "text": "U"}, {"box": [334, 514, 360, 528], "id": 282, "text": "T"}, {"box": [334, 514, 360, 528], "id": 283, "text": " "}, {"box": [367, 509, 389, 528], "id": 284, "text": "O"}, {"box": [367, 509, 389, 528], "id": 285, "text": "F"}, {"box": [367, 509, 389, 528], "id": 286, "text": " "}, {"box": [292, 531, 332, 544], "id": 287, "text": "1"}, {"box": [292, 531, 332, 544], "id": 288, "text": "9"}, {"box": [292, 531, 332, 544], "id": 289, "text": "8"}, {"box": [292, 531, 332, 544], "id": 290, "text": "7"}, {"box": [292, 531, 332, 544], "id": 291, "text": " "}, {"box": [337, 527, 385, 548], "id": 292, "text": "B"}, {"box": [337, 527, 385, 548], "id": 293, "text": "U"}, {"box": [337, 527, 385, 548], "id": 294, "text": "D"}, {"box": [337, 527, 385, 548], "id": 295, "text": "G"}, {"box": [337, 527, 385, 548], "id": 296, "text": "E"}, {"box": [337, 527, 385, 548], "id": 297, "text": "T"}]}, {"box": [5, 950, 228, 970], "text": "PRODUCED FROM B&W WEB SITE", "id": 19, "words": [{"box": [5, 950, 85, 969], "id": 299, "text": "P"}, {"box": [5, 950, 85, 969], "id": 300, "text": "R"}, {"box": [5, 950, 85, 969], "id": 301, "text": "O"}, {"box": [5, 950, 85, 969], "id": 302, "text": "D"}, {"box": [5, 950, 85, 969], "id": 303, "text": "U"}, {"box": [5, 950, 85, 969], "id": 304, "text": "C"}, {"box": [5, 950, 85, 969], "id": 305, "text": "E"}, {"box": [5, 950, 85, 969], "id": 306, "text": "D"}, {"box": [5, 950, 85, 969], "id": 307, "text": " "}, {"box": [86, 950, 125, 970], "id": 308, "text": "F"}, {"box": [86, 950, 125, 970], "id": 309, "text": "R"}, {"box": [86, 950, 125, 970], "id": 310, "text": "O"}, {"box": [86, 950, 125, 970], "id": 311, "text": "M"}, {"box": [86, 950, 125, 970], "id": 312, "text": " "}, {"box": [127, 954, 160, 969], "id": 313, "text": "B"}, {"box": [127, 954, 160, 969], "id": 314, "text": "&"}, {"box": [127, 954, 160, 969], "id": 315, "text": "W"}, {"box": [127, 954, 160, 969], "id": 316, "text": " "}, {"box": [163, 950, 191, 969], "id": 317, "text": "W"}, {"box": [163, 950, 191, 969], "id": 318, "text": "E"}, {"box": [163, 950, 191, 969], "id": 319, "text": "B"}, {"box": [163, 950, 191, 969], "id": 320, "text": " "}, {"box": [195, 950, 228, 969], "id": 321, "text": "S"}, {"box": [195, 950, 228, 969], "id": 322, "text": "I"}, {"box": [195, 950, 228, 969], "id": 323, "text": "T"}, {"box": [195, 950, 228, 969], "id": 324, "text": "E"}]}], "uid": "./training_data/images/12052385.png", "img": {"fname": "./training_data/images/12052385.png", "height": 1000, "width": 773, "image_url": "12052385.png", "url": "12052385.png", "cls_id": 0}, "label_entities": {"question": {"entity_id": 0, "label": "question", "alias": [], "word_idx": [[0, 1, 2, 3, 4], [5, 6, 7, 8, 9, 10, 11, 12, 13, 14, 15, 16, 17], [18, 19, 20, 21, 22, 23, 24, 25, 26, 27], [28, 29, 30, 31, 32, 33, 34, 35, 36, 37, 38], [63, 64, 65, 66, 67, 68, 69, 70, 71, 72, 73, 74], [226, 227, 228, 229, 230, 231, 232, 233, 234, 235, 236, 237, 238, 239], [240, 241, 242, 243, 244, 245, 246, 247, 248, 249, 250, 251, 252, 253, 254, 255, 256], [257, 258, 259, 260, 261, 262, 263, 264, 265, 266, 267, 268, 269, 270, 271, 272, 273, 274], [275, 276, 277, 278, 279, 280, 281, 282, 283, 284, 285, 286, 287, 288, 289, 290, 291, 292, 293, 294, 295, 296, 297, 298]]}, "answer": {"entity_id": 1, "label": "answer", "alias": [], "word_idx": [[39, 40, 41, 42], [88, 89, 90, 91, 92, 93, 94, 95, 96, 97, 98, 99, 100, 101, 102, 103, 104, 105, 106], [107, 108, 109, 110, 111, 112, 113, 114, 115, 116, 117, 118, 119, 120, 121, 122, 123, 124, 125, 126, 127, 128, 129, 130, 131, 132, 133, 134, 135, 136, 137, 138, 139, 140, 141, 142, 143, 144, 145, 146, 147, 148, 149, 150, 151, 152, 153, 154, 155, 156, 157], [158, 159, 160, 161, 162, 163, 164, 165, 166, 167, 168], [169, 170, 171, 172, 173, 174, 175, 176, 177, 178, 179, 180, 181], [182, 183, 184, 185, 186, 187, 188, 189, 190, 191, 192, 193, 194, 195, 196, 197, 198, 199, 200, 201, 202]]}}, "label_linkings": [[0, 9], [1, 10], [2, 12], [18, 4], [7, 8], [15, 11], [16, 13]], "tag": "12052385", "label_groups": [[[0, 1, 2, 3, 4], [88, 89, 90, 91, 92, 93, 94, 95, 96, 97, 98, 99, 100, 101, 102, 103, 104, 105, 106]], [[5, 6, 7, 8, 9, 10, 11, 12, 13, 14, 15, 16, 17], [107, 108, 109, 110, 111, 112, 113, 114, 115, 116, 117, 118, 119, 120, 121, 122, 123, 124, 125, 126, 127, 128, 129, 130, 131, 132, 133, 134, 135, 136, 137, 138, 139, 140, 141, 142, 143, 144, 145, 146, 147, 148, 149, 150, 151, 152, 153, 154, 155, 156, 157]], [[18, 19, 20, 21, 22, 23, 24, 25, 26, 27], [169, 170, 171, 172, 173, 174, 175, 176, 177, 178, 179, 180, 181]], [[275, 276, 277, 278, 279, 280, 281, 282, 283, 284, 285, 286, 287, 288, 289, 290, 291, 292, 293, 294, 295, 296, 297, 298], [39, 40, 41, 42]], [[226, 227, 228, 229, 230, 231, 232, 233, 234, 235, 236, 237, 238, 239], [158, 159, 160, 161, 162, 163, 164, 165, 166, 167, 168]], [[240, 241, 242, 243, 244, 245, 246, 247, 248, 249, 250, 251, 252, 253, 254, 255, 256], [182, 183, 184, 185, 186, 187, 188, 189, 190, 191, 192, 193, 194, 195, 196, 197, 198, 199, 200, 201, 202]]]}