{"document": [{"box": [61, 127, 143, 211], "text": "å", "id": 0, "words": [{"box": [61, 127, 143, 211], "id": 0, "text": "å"}]}, {"box": [102, 345, 129, 359], "text": "TO:", "id": 1, "words": [{"box": [102, 345, 129, 359], "id": 2, "text": "T"}, {"box": [102, 345, 129, 359], "id": 3, "text": "O"}, {"box": [102, 345, 129, 359], "id": 4, "text": ":"}]}, {"box": [102, 406, 147, 423], "text": "DATE:", "id": 2, "words": [{"box": [102, 406, 147, 423], "id": 6, "text": "D"}, {"box": [102, 406, 147, 423], "id": 7, "text": "A"}, {"box": [102, 406, 147, 423], "id": 8, "text": "T"}, {"box": [102, 406, 147, 423], "id": 9, "text": "E"}, {"box": [102, 406, 147, 423], "id": 10, "text": ":"}]}, {"box": [461, 440, 475, 455], "text": "3", "id": 3, "words": [{"box": [461, 440, 475, 455], "id": 12, "text": "3"}]}, {"box": [249, 84, 274, 98], "text": "Fax:", "id": 4, "words": [{"box": [249, 84, 274, 98], "id": 14, "text": "F"}, {"box": [249, 84, 274, 98], "id": 15, "text": "a"}, {"box": [249, 84, 274, 98], "id": 16, "text": "x"}, {"box": [249, 84, 274, 98], "id": 17, "text": ":"}]}, {"box": [103, 691, 139, 708], "text": "NOTE:", "id": 5, "words": [{"box": [103, 691, 139, 708], "id": 19, "text": "N"}, {"box": [103, 691, 139, 708], "id": 20, "text": "O"}, {"box": [103, 691, 139, 708], "id": 21, "text": "T"}, {"box": [103, 691, 139, 708], "id": 22, "text": "E"}, {"box": [103, 691, 139, 708], "id": 23, "text": ":"}]}, {"box": [633, 775, 653, 874], "text": "82092117", "id": 6, "words": [{"box": [633, 775, 653, 874], "id": 25, "text": "8"}, {"box": [633, 775, 653, 874], "id": 26, "text": "2"}, {"box": [633, 775, 653, 874], "id": 27, "text": "0"}, {"box": [633, 775, 653, 874], "id": 28, "text": "9"}, {"box": [633, 775, 653, 874], "id": 29, "text": "2"}, {"box": [633, 775, 653, 874], "id": 30, "text": "1"}, {"box": [633, 775, 653, 874], "id": 31, "text": "1"}, {"box": [633, 775, 653, 874], "id": 32, "text": "7"}]}, {"box": [275, 82, 354, 101], "text": "614 -466 -5087", "id": 7, "words": [{"box": [275, 85, 295, 99], "id": 34, "text": "6"}, {"box": [275, 85, 295, 99], "id": 35, "text": "1"}, {"box": [275, 85, 295, 99], "id": 36, "text": "4"}, {"box": [275, 85, 295, 99], "id": 37, "text": " "}, {"box": [296, 84, 320, 101], "id": 38, "text": "-"}, {"box": [296, 84, 320, 101], "id": 39, "text": "4"}, {"box": [296, 84, 320, 101], "id": 40, "text": "6"}, {"box": [296, 84, 320, 101], "id": 41, "text": "6"}, {"box": [296, 84, 320, 101], "id": 42, "text": " "}, {"box": [320, 82, 354, 100], "id": 43, "text": "-"}, {"box": [320, 82, 354, 100], "id": 44, "text": "5"}, {"box": [320, 82, 354, 100], "id": 45, "text": "0"}, {"box": [320, 82, 354, 100], "id": 46, "text": "8"}, {"box": [320, 82, 354, 100], "id": 47, "text": "7"}]}, {"box": [419, 82, 589, 101], "text": "Dec 10 '98 17 :46 P. 01", "id": 8, "words": [{"box": [419, 84, 439, 98], "id": 49, "text": "D"}, {"box": [419, 84, 439, 98], "id": 50, "text": "e"}, {"box": [419, 84, 439, 98], "id": 51, "text": "c"}, {"box": [419, 84, 439, 98], "id": 52, "text": " "}, {"box": [444, 85, 459, 99], "id": 53, "text": "1"}, {"box": [444, 85, 459, 99], "id": 54, "text": "0"}, {"box": [444, 85, 459, 99], "id": 55, "text": " "}, {"box": [464, 84, 484, 98], "id": 56, "text": "'"}, {"box": [464, 84, 484, 98], "id": 57, "text": "9"}, {"box": [464, 84, 484, 98], "id": 58, "text": "8"}, {"box": [464, 84, 484, 98], "id": 59, "text": " "}, {"box": [499, 85, 516, 98], "id": 60, "text": "1"}, {"box": [499, 85, 516, 98], "id": 61, "text": "7"}, {"box": [499, 85, 516, 98], "id": 62, "text": " "}, {"box": [515, 84, 535, 101], "id": 63, "text": ":"}, {"box": [515, 84, 535, 101], "id": 64, "text": "4"}, {"box": [515, 84, 535, 101], "id": 65, "text": "6"}, {"box": [515, 84, 535, 101], "id": 66, "text": " "}, {"box": [554, 82, 574, 97], "id": 67, "text": "P"}, {"box": [554, 82, 574, 97], "id": 68, "text": "."}, {"box": [554, 82, 574, 97], "id": 69, "text": " "}, {"box": [574, 84, 589, 99], "id": 70, "text": "0"}, {"box": [574, 84, 589, 99], "id": 71, "text": "1"}]}, {"box": [103, 84, 246, 100], "text": "ATT. GEN. ADMIN. OFFICE", "id": 9, "words": [{"box": [103, 85, 127, 100], "id": 73, "text": "A"}, {"box": [103, 85, 127, 100], "id": 74, "text": "T"}, {"box": [103, 85, 127, 100], "id": 75, "text": "T"}, {"box": [103, 85, 127, 100], "id": 76, "text": "."}, {"box": [103, 85, 127, 100], "id": 77, "text": " "}, {"box": [133, 85, 160, 99], "id": 78, "text": "G"}, {"box": [133, 85, 160, 99], "id": 79, "text": "E"}, {"box": [133, 85, 160, 99], "id": 80, "text": "N"}, {"box": [133, 85, 160, 99], "id": 81, "text": "."}, {"box": [133, 85, 160, 99], "id": 82, "text": " "}, {"box": [166, 84, 204, 99], "id": 83, "text": "A"}, {"box": [166, 84, 204, 99], "id": 84, "text": "D"}, {"box": [166, 84, 204, 99], "id": 85, "text": "M"}, {"box": [166, 84, 204, 99], "id": 86, "text": "I"}, {"box": [166, 84, 204, 99], "id": 87, "text": "N"}, {"box": [166, 84, 204, 99], "id": 88, "text": "."}, {"box": [166, 84, 204, 99], "id": 89, "text": " "}, {"box": [207, 84, 246, 98], "id": 90, "text": "O"}, {"box": [207, 84, 246, 98], "id": 91, "text": "F"}, {"box": [207, 84, 246, 98], "id": 92, "text": "F"}, {"box": [207, 84, 246, 98], "id": 93, "text": "I"}, {"box": [207, 84, 246, 98], "id": 94, "text": "C"}, {"box": [207, 84, 246, 98], "id": 95, "text": "E"}]}, {"box": [147, 148, 305, 191], "text": "Attorney General Betty D. Montgomery", "id": 10, "words": [{"box": [147, 148, 213, 168], "id": 97, "text": "A"}, {"box": [147, 148, 213, 168], "id": 98, "text": "t"}, {"box": [147, 148, 213, 168], "id": 99, "text": "t"}, {"box": [147, 148, 213, 168], "id": 100, "text": "o"}, {"box": [147, 148, 213, 168], "id": 101, "text": "r"}, {"box": [147, 148, 213, 168], "id": 102, "text": "n"}, {"box": [147, 148, 213, 168], "id": 103, "text": "e"}, {"box": [147, 148, 213, 168], "id": 104, "text": "y"}, {"box": [147, 148, 213, 168], "id": 105, "text": " "}, {"box": [216, 151, 275, 168], "id": 106, "text": "G"}, {"box": [216, 151, 275, 168], "id": 107, "text": "e"}, {"box": [216, 151, 275, 168], "id": 108, "text": "n"}, {"box": [216, 151, 275, 168], "id": 109, "text": "e"}, {"box": [216, 151, 275, 168], "id": 110, "text": "r"}, {"box": [216, 151, 275, 168], "id": 111, "text": "a"}, {"box": [216, 151, 275, 168], "id": 112, "text": "l"}, {"box": [216, 151, 275, 168], "id": 113, "text": " "}, {"box": [148, 172, 187, 190], "id": 114, "text": "B"}, {"box": [148, 172, 187, 190], "id": 115, "text": "e"}, {"box": [148, 172, 187, 190], "id": 116, "text": "t"}, {"box": [148, 172, 187, 190], "id": 117, "text": "t"}, {"box": [148, 172, 187, 190], "id": 118, "text": "y"}, {"box": [148, 172, 187, 190], "id": 119, "text": " "}, {"box": [191, 169, 206, 187], "id": 120, "text": "D"}, {"box": [191, 169, 206, 187], "id": 121, "text": "."}, {"box": [191, 169, 206, 187], "id": 122, "text": " "}, {"box": [211, 170, 305, 191], "id": 123, "text": "M"}, {"box": [211, 170, 305, 191], "id": 124, "text": "o"}, {"box": [211, 170, 305, 191], "id": 125, "text": "n"}, {"box": [211, 170, 305, 191], "id": 126, "text": "t"}, {"box": [211, 170, 305, 191], "id": 127, "text": "g"}, {"box": [211, 170, 305, 191], "id": 128, "text": "o"}, {"box": [211, 170, 305, 191], "id": 129, "text": "m"}, {"box": [211, 170, 305, 191], "id": 130, "text": "e"}, {"box": [211, 170, 305, 191], "id": 131, "text": "r"}, {"box": [211, 170, 305, 191], "id": 132, "text": "y"}]}, {"box": [264, 249, 467, 281], "text": "CONFIDENTIAL FACSIMILE TRANSMISSION COVER SHEET", "id": 11, "words": [{"box": [275, 249, 377, 267], "id": 134, "text": "C"}, {"box": [275, 249, 377, 267], "id": 135, "text": "O"}, {"box": [275, 249, 377, 267], "id": 136, "text": "N"}, {"box": [275, 249, 377, 267], "id": 137, "text": "F"}, {"box": [275, 249, 377, 267], "id": 138, "text": "I"}, {"box": [275, 249, 377, 267], "id": 139, "text": "D"}, {"box": [275, 249, 377, 267], "id": 140, "text": "E"}, {"box": [275, 249, 377, 267], "id": 141, "text": "N"}, {"box": [275, 249, 377, 267], "id": 142, "text": "T"}, {"box": [275, 249, 377, 267], "id": 143, "text": "I"}, {"box": [275, 249, 377, 267], "id": 144, "text": "A"}, {"box": [275, 249, 377, 267], "id": 145, "text": "L"}, {"box": [275, 249, 377, 267], "id": 146, "text": " "}, {"box": [380, 250, 457, 267], "id": 147, "text": "F"}, {"box": [380, 250, 457, 267], "id": 148, "text": "A"}, {"box": [380, 250, 457, 267], "id": 149, "text": "C"}, {"box": [380, 250, 457, 267], "id": 150, "text": "S"}, {"box": [380, 250, 457, 267], "id": 151, "text": "I"}, {"box": [380, 250, 457, 267], "id": 152, "text": "M"}, {"box": [380, 250, 457, 267], "id": 153, "text": "I"}, {"box": [380, 250, 457, 267], "id": 154, "text": "L"}, {"box": [380, 250, 457, 267], "id": 155, "text": "E"}, {"box": [380, 250, 457, 267], "id": 156, "text": " "}, {"box": [264, 267, 369, 281], "id": 157, "text": "T"}, {"box": [264, 267, 369, 281], "id": 158, "text": "R"}, {"box": [264, 267, 369, 281], "id": 159, "text": "A"}, {"box": [264, 267, 369, 281], "id": 160, "text": "N"}, {"box": [264, 267, 369, 281], "id": 161, "text": "S"}, {"box": [264, 267, 369, 281], "id": 162, "text": "M"}, {"box": [264, 267, 369, 281], "id": 163, "text": "I"}, {"box": [264, 267, 369, 281], "id": 164, "text": "S"}, {"box": [264, 267, 369, 281], "id": 165, "text": "S"}, {"box": [264, 267, 369, 281], "id": 166, "text": "I"}, {"box": [264, 267, 369, 281], "id": 167, "text": "O"}, {"box": [264, 267, 369, 281], "id": 168, "text": "N"}, {"box": [264, 267, 369, 281], "id": 169, "text": " "}, {"box": [369, 267, 422, 281], "id": 170, "text": "C"}, {"box": [369, 267, 422, 281], "id": 171, "text": "O"}, {"box": [369, 267, 422, 281], "id": 172, "text": "V"}, {"box": [369, 267, 422, 281], "id": 173, "text": "E"}, {"box": [369, 267, 422, 281], "id": 174, "text": "R"}, {"box": [369, 267, 422, 281], "id": 175, "text": " "}, {"box": [420, 267, 467, 281], "id": 176, "text": "S"}, {"box": [420, 267, 467, 281], "id": 177, "text": "H"}, {"box": [420, 267, 467, 281], "id": 178, "text": "E"}, {"box": [420, 267, 467, 281], "id": 179, "text": "E"}, {"box": [420, 267, 467, 281], "id": 180, "text": "T"}]}, {"box": [352, 296, 438, 314], "text": "(614) 466- 5087", "id": 12, "words": [{"box": [352, 297, 383, 314], "id": 182, "text": "("}, {"box": [352, 297, 383, 314], "id": 183, "text": "6"}, {"box": [352, 297, 383, 314], "id": 184, "text": "1"}, {"box": [352, 297, 383, 314], "id": 185, "text": "4"}, {"box": [352, 297, 383, 314], "id": 186, "text": ")"}, {"box": [352, 297, 383, 314], "id": 187, "text": " "}, {"box": [384, 296, 405, 313], "id": 188, "text": "4"}, {"box": [384, 296, 405, 313], "id": 189, "text": "6"}, {"box": [384, 296, 405, 313], "id": 190, "text": "6"}, {"box": [384, 296, 405, 313], "id": 191, "text": "-"}, {"box": [384, 296, 405, 313], "id": 192, "text": " "}, {"box": [406, 297, 438, 312], "id": 193, "text": "5"}, {"box": [406, 297, 438, 312], "id": 194, "text": "0"}, {"box": [406, 297, 438, 312], "id": 195, "text": "8"}, {"box": [406, 297, 438, 312], "id": 196, "text": "7"}]}, {"box": [289, 296, 351, 311], "text": "FAX NO.", "id": 13, "words": [{"box": [289, 297, 323, 311], "id": 198, "text": "F"}, {"box": [289, 297, 323, 311], "id": 199, "text": "A"}, {"box": [289, 297, 323, 311], "id": 200, "text": "X"}, {"box": [289, 297, 323, 311], "id": 201, "text": " "}, {"box": [324, 296, 351, 311], "id": 202, "text": "N"}, {"box": [324, 296, 351, 311], "id": 203, "text": "O"}, {"box": [324, 296, 351, 311], "id": 204, "text": "."}]}, {"box": [142, 342, 236, 360], "text": "George Baroody", "id": 14, "words": [{"box": [142, 345, 185, 359], "id": 206, "text": "G"}, {"box": [142, 345, 185, 359], "id": 207, "text": "e"}, {"box": [142, 345, 185, 359], "id": 208, "text": "o"}, {"box": [142, 345, 185, 359], "id": 209, "text": "r"}, {"box": [142, 345, 185, 359], "id": 210, "text": "g"}, {"box": [142, 345, 185, 359], "id": 211, "text": "e"}, {"box": [142, 345, 185, 359], "id": 212, "text": " "}, {"box": [187, 342, 236, 360], "id": 213, "text": "B"}, {"box": [187, 342, 236, 360], "id": 214, "text": "a"}, {"box": [187, 342, 236, 360], "id": 215, "text": "r"}, {"box": [187, 342, 236, 360], "id": 216, "text": "o"}, {"box": [187, 342, 236, 360], "id": 217, "text": "o"}, {"box": [187, 342, 236, 360], "id": 218, "text": "d"}, {"box": [187, 342, 236, 360], "id": 219, "text": "y"}]}, {"box": [223, 376, 312, 393], "text": "(336) 335- 7392", "id": 15, "words": [{"box": [223, 376, 254, 393], "id": 221, "text": "("}, {"box": [223, 376, 254, 393], "id": 222, "text": "3"}, {"box": [223, 376, 254, 393], "id": 223, "text": "3"}, {"box": [223, 376, 254, 393], "id": 224, "text": "6"}, {"box": [223, 376, 254, 393], "id": 225, "text": ")"}, {"box": [223, 376, 254, 393], "id": 226, "text": " "}, {"box": [257, 376, 284, 390], "id": 227, "text": "3"}, {"box": [257, 376, 284, 390], "id": 228, "text": "3"}, {"box": [257, 376, 284, 390], "id": 229, "text": "5"}, {"box": [257, 376, 284, 390], "id": 230, "text": "-"}, {"box": [257, 376, 284, 390], "id": 231, "text": " "}, {"box": [284, 376, 312, 391], "id": 232, "text": "7"}, {"box": [284, 376, 312, 391], "id": 233, "text": "3"}, {"box": [284, 376, 312, 391], "id": 234, "text": "9"}, {"box": [284, 376, 312, 391], "id": 235, "text": "2"}]}, {"box": [102, 374, 200, 391], "text": "FAX NUMBER:", "id": 16, "words": [{"box": [102, 374, 131, 391], "id": 237, "text": "F"}, {"box": [102, 374, 131, 391], "id": 238, "text": "A"}, {"box": [102, 374, 131, 391], "id": 239, "text": "X"}, {"box": [102, 374, 131, 391], "id": 240, "text": " "}, {"box": [134, 374, 200, 391], "id": 241, "text": "N"}, {"box": [134, 374, 200, 391], "id": 242, "text": "U"}, {"box": [134, 374, 200, 391], "id": 243, "text": "M"}, {"box": [134, 374, 200, 391], "id": 244, "text": "B"}, {"box": [134, 374, 200, 391], "id": 245, "text": "E"}, {"box": [134, 374, 200, 391], "id": 246, "text": "R"}, {"box": [134, 374, 200, 391], "id": 247, "text": ":"}]}, {"box": [383, 376, 500, 391], "text": "PHONE NUMBER:", "id": 17, "words": [{"box": [383, 376, 433, 391], "id": 249, "text": "P"}, {"box": [383, 376, 433, 391], "id": 250, "text": "H"}, {"box": [383, 376, 433, 391], "id": 251, "text": "O"}, {"box": [383, 376, 433, 391], "id": 252, "text": "N"}, {"box": [383, 376, 433, 391], "id": 253, "text": "E"}, {"box": [383, 376, 433, 391], "id": 254, "text": " "}, {"box": [436, 377, 500, 391], "id": 255, "text": "N"}, {"box": [436, 377, 500, 391], "id": 256, "text": "U"}, {"box": [436, 377, 500, 391], "id": 257, "text": "M"}, {"box": [436, 377, 500, 391], "id": 258, "text": "B"}, {"box": [436, 377, 500, 391], "id": 259, "text": "E"}, {"box": [436, 377, 500, 391], "id": 260, "text": "R"}, {"box": [436, 377, 500, 391], "id": 261, "text": ":"}]}, {"box": [504, 376, 592, 393], "text": "(336) 335- 7363", "id": 18, "words": [{"box": [504, 376, 535, 393], "id": 263, "text": "("}, {"box": [504, 376, 535, 393], "id": 264, "text": "3"}, {"box": [504, 376, 535, 393], "id": 265, "text": "3"}, {"box": [504, 376, 535, 393], "id": 266, "text": "6"}, {"box": [504, 376, 535, 393], "id": 267, "text": ")"}, {"box": [504, 376, 535, 393], "id": 268, "text": " "}, {"box": [536, 378, 563, 392], "id": 269, "text": "3"}, {"box": [536, 378, 563, 392], "id": 270, "text": "3"}, {"box": [536, 378, 563, 392], "id": 271, "text": "5"}, {"box": [536, 378, 563, 392], "id": 272, "text": "-"}, {"box": [536, 378, 563, 392], "id": 273, "text": " "}, {"box": [563, 376, 592, 390], "id": 274, "text": "7"}, {"box": [563, 376, 592, 390], "id": 275, "text": "3"}, {"box": [563, 376, 592, 390], "id": 276, "text": "6"}, {"box": [563, 376, 592, 390], "id": 277, "text": "3"}]}, {"box": [102, 439, 421, 457], "text": "NUMBER OF PAGES INCLUDING COVER SHEET:", "id": 19, "words": [{"box": [102, 439, 168, 457], "id": 279, "text": "N"}, {"box": [102, 439, 168, 457], "id": 280, "text": "U"}, {"box": [102, 439, 168, 457], "id": 281, "text": "M"}, {"box": [102, 439, 168, 457], "id": 282, "text": "B"}, {"box": [102, 439, 168, 457], "id": 283, "text": "E"}, {"box": [102, 439, 168, 457], "id": 284, "text": "R"}, {"box": [102, 439, 168, 457], "id": 285, "text": " "}, {"box": [168, 439, 188, 456], "id": 286, "text": "O"}, {"box": [168, 439, 188, 456], "id": 287, "text": "F"}, {"box": [168, 439, 188, 456], "id": 288, "text": " "}, {"box": [189, 440, 234, 457], "id": 289, "text": "P"}, {"box": [189, 440, 234, 457], "id": 290, "text": "A"}, {"box": [189, 440, 234, 457], "id": 291, "text": "G"}, {"box": [189, 440, 234, 457], "id": 292, "text": "E"}, {"box": [189, 440, 234, 457], "id": 293, "text": "S"}, {"box": [189, 440, 234, 457], "id": 294, "text": " "}, {"box": [237, 439, 315, 456], "id": 295, "text": "I"}, {"box": [237, 439, 315, 456], "id": 296, "text": "N"}, {"box": [237, 439, 315, 456], "id": 297, "text": "C"}, {"box": [237, 439, 315, 456], "id": 298, "text": "L"}, {"box": [237, 439, 315, 456], "id": 299, "text": "U"}, {"box": [237, 439, 315, 456], "id": 300, "text": "D"}, {"box": [237, 439, 315, 456], "id": 301, "text": "I"}, {"box": [237, 439, 315, 456], "id": 302, "text": "N"}, {"box": [237, 439, 315, 456], "id": 303, "text": "G"}, {"box": [237, 439, 315, 456], "id": 304, "text": " "}, {"box": [318, 439, 368, 454], "id": 305, "text": "C"}, {"box": [318, 439, 368, 454], "id": 306, "text": "O"}, {"box": [318, 439, 368, 454], "id": 307, "text": "V"}, {"box": [318, 439, 368, 454], "id": 308, "text": "E"}, {"box": [318, 439, 368, 454], "id": 309, "text": "R"}, {"box": [318, 439, 368, 454], "id": 310, "text": " "}, {"box": [369, 439, 421, 456], "id": 311, "text": "S"}, {"box": [369, 439, 421, 456], "id": 312, "text": "H"}, {"box": [369, 439, 421, 456], "id": 313, "text": "E"}, {"box": [369, 439, 421, 456], "id": 314, "text": "E"}, {"box": [369, 439, 421, 456], "id": 315, "text": "T"}, {"box": [369, 439, 421, 456], "id": 316, "text": ":"}]}, {"box": [304, 471, 537, 487], "text": "June Flynn for Eric Brown/ (614) 466- 8980", "id": 20, "words": [{"box": [304, 473, 329, 486], "id": 318, "text": "J"}, {"box": [304, 473, 329, 486], "id": 319, "text": "u"}, {"box": [304, 473, 329, 486], "id": 320, "text": "n"}, {"box": [304, 473, 329, 486], "id": 321, "text": "e"}, {"box": [304, 473, 329, 486], "id": 322, "text": " "}, {"box": [332, 471, 364, 485], "id": 323, "text": "F"}, {"box": [332, 471, 364, 485], "id": 324, "text": "l"}, {"box": [332, 471, 364, 485], "id": 325, "text": "y"}, {"box": [332, 471, 364, 485], "id": 326, "text": "n"}, {"box": [332, 471, 364, 485], "id": 327, "text": "n"}, {"box": [332, 471, 364, 485], "id": 328, "text": " "}, {"box": [367, 473, 382, 486], "id": 329, "text": "f"}, {"box": [367, 473, 382, 486], "id": 330, "text": "o"}, {"box": [367, 473, 382, 486], "id": 331, "text": "r"}, {"box": [367, 473, 382, 486], "id": 332, "text": " "}, {"box": [385, 471, 407, 485], "id": 333, "text": "E"}, {"box": [385, 471, 407, 485], "id": 334, "text": "r"}, {"box": [385, 471, 407, 485], "id": 335, "text": "i"}, {"box": [385, 471, 407, 485], "id": 336, "text": "c"}, {"box": [385, 471, 407, 485], "id": 337, "text": " "}, {"box": [411, 472, 452, 486], "id": 338, "text": "B"}, {"box": [411, 472, 452, 486], "id": 339, "text": "r"}, {"box": [411, 472, 452, 486], "id": 340, "text": "o"}, {"box": [411, 472, 452, 486], "id": 341, "text": "w"}, {"box": [411, 472, 452, 486], "id": 342, "text": "n"}, {"box": [411, 472, 452, 486], "id": 343, "text": "/"}, {"box": [411, 472, 452, 486], "id": 344, "text": " "}, {"box": [450, 472, 481, 487], "id": 345, "text": "("}, {"box": [450, 472, 481, 487], "id": 346, "text": "6"}, {"box": [450, 472, 481, 487], "id": 347, "text": "1"}, {"box": [450, 472, 481, 487], "id": 348, "text": "4"}, {"box": [450, 472, 481, 487], "id": 349, "text": ")"}, {"box": [450, 472, 481, 487], "id": 350, "text": " "}, {"box": [482, 472, 504, 486], "id": 351, "text": "4"}, {"box": [482, 472, 504, 486], "id": 352, "text": "6"}, {"box": [482, 472, 504, 486], "id": 353, "text": "6"}, {"box": [482, 472, 504, 486], "id": 354, "text": "-"}, {"box": [482, 472, 504, 486], "id": 355, "text": " "}, {"box": [506, 472, 537, 487], "id": 356, "text": "8"}, {"box": [506, 472, 537, 487], "id": 357, "text": "9"}, {"box": [506, 472, 537, 487], "id": 358, "text": "8"}, {"box": [506, 472, 537, 487], "id": 359, "text": "0"}]}, {"box": [98, 471, 280, 488], "text": "SENDER /PHONE NUMBER:", "id": 21, "words": [{"box": [98, 471, 158, 486], "id": 361, "text": "S"}, {"box": [98, 471, 158, 486], "id": 362, "text": "E"}, {"box": [98, 471, 158, 486], "id": 363, "text": "N"}, {"box": [98, 471, 158, 486], "id": 364, "text": "D"}, {"box": [98, 471, 158, 486], "id": 365, "text": "E"}, {"box": [98, 471, 158, 486], "id": 366, "text": "R"}, {"box": [98, 471, 158, 486], "id": 367, "text": " "}, {"box": [159, 472, 212, 486], "id": 368, "text": "/"}, {"box": [159, 472, 212, 486], "id": 369, "text": "P"}, {"box": [159, 472, 212, 486], "id": 370, "text": "H"}, {"box": [159, 472, 212, 486], "id": 371, "text": "O"}, {"box": [159, 472, 212, 486], "id": 372, "text": "N"}, {"box": [159, 472, 212, 486], "id": 373, "text": "E"}, {"box": [159, 472, 212, 486], "id": 374, "text": " "}, {"box": [214, 471, 280, 488], "id": 375, "text": "N"}, {"box": [214, 471, 280, 488], "id": 376, "text": "U"}, {"box": [214, 471, 280, 488], "id": 377, "text": "M"}, {"box": [214, 471, 280, 488], "id": 378, "text": "B"}, {"box": [214, 471, 280, 488], "id": 379, "text": "E"}, {"box": [214, 471, 280, 488], "id": 380, "text": "R"}, {"box": [214, 471, 280, 488], "id": 381, "text": ":"}]}, {"box": [103, 503, 274, 520], "text": "SPECIAL INSTRUCTIONS:", "id": 22, "words": [{"box": [103, 503, 163, 520], "id": 383, "text": "S"}, {"box": [103, 503, 163, 520], "id": 384, "text": "P"}, {"box": [103, 503, 163, 520], "id": 385, "text": "E"}, {"box": [103, 503, 163, 520], "id": 386, "text": "C"}, {"box": [103, 503, 163, 520], "id": 387, "text": "I"}, {"box": [103, 503, 163, 520], "id": 388, "text": "A"}, {"box": [103, 503, 163, 520], "id": 389, "text": "L"}, {"box": [103, 503, 163, 520], "id": 390, "text": " "}, {"box": [165, 503, 274, 520], "id": 391, "text": "I"}, {"box": [165, 503, 274, 520], "id": 392, "text": "N"}, {"box": [165, 503, 274, 520], "id": 393, "text": "S"}, {"box": [165, 503, 274, 520], "id": 394, "text": "T"}, {"box": [165, 503, 274, 520], "id": 395, "text": "R"}, {"box": [165, 503, 274, 520], "id": 396, "text": "U"}, {"box": [165, 503, 274, 520], "id": 397, "text": "C"}, {"box": [165, 503, 274, 520], "id": 398, "text": "T"}, {"box": [165, 503, 274, 520], "id": 399, "text": "I"}, {"box": [165, 503, 274, 520], "id": 400, "text": "O"}, {"box": [165, 503, 274, 520], "id": 401, "text": "N"}, {"box": [165, 503, 274, 520], "id": 402, "text": "S"}, {"box": [165, 503, 274, 520], "id": 403, "text": ":"}]}, {"box": [175, 599, 556, 646], "text": "IF YOU DO NOT RECEIVE ANY OF THE PAGES PROPERLY, PLEASE CONTACT SENDER AS SOON AS POSSIBLE", "id": 23, "words": [{"box": [175, 601, 190, 614], "id": 405, "text": "I"}, {"box": [175, 601, 190, 614], "id": 406, "text": "F"}, {"box": [175, 601, 190, 614], "id": 407, "text": " "}, {"box": [191, 601, 222, 615], "id": 408, "text": "Y"}, {"box": [191, 601, 222, 615], "id": 409, "text": "O"}, {"box": [191, 601, 222, 615], "id": 410, "text": "U"}, {"box": [191, 601, 222, 615], "id": 411, "text": " "}, {"box": [225, 601, 245, 614], "id": 412, "text": "D"}, {"box": [225, 601, 245, 614], "id": 413, "text": "O"}, {"box": [225, 601, 245, 614], "id": 414, "text": " "}, {"box": [249, 599, 277, 613], "id": 415, "text": "N"}, {"box": [249, 599, 277, 613], "id": 416, "text": "O"}, {"box": [249, 599, 277, 613], "id": 417, "text": "T"}, {"box": [249, 599, 277, 613], "id": 418, "text": " "}, {"box": [281, 601, 341, 615], "id": 419, "text": "R"}, {"box": [281, 601, 341, 615], "id": 420, "text": "E"}, {"box": [281, 601, 341, 615], "id": 421, "text": "C"}, {"box": [281, 601, 341, 615], "id": 422, "text": "E"}, {"box": [281, 601, 341, 615], "id": 423, "text": "I"}, {"box": [281, 601, 341, 615], "id": 424, "text": "V"}, {"box": [281, 601, 341, 615], "id": 425, "text": "E"}, {"box": [281, 601, 341, 615], "id": 426, "text": " "}, {"box": [344, 601, 373, 612], "id": 427, "text": "A"}, {"box": [344, 601, 373, 612], "id": 428, "text": "N"}, {"box": [344, 601, 373, 612], "id": 429, "text": "Y"}, {"box": [344, 601, 373, 612], "id": 430, "text": " "}, {"box": [376, 599, 394, 612], "id": 431, "text": "O"}, {"box": [376, 599, 394, 612], "id": 432, "text": "F"}, {"box": [376, 599, 394, 612], "id": 433, "text": " "}, {"box": [397, 599, 426, 613], "id": 434, "text": "T"}, {"box": [397, 599, 426, 613], "id": 435, "text": "H"}, {"box": [397, 599, 426, 613], "id": 436, "text": "E"}, {"box": [397, 599, 426, 613], "id": 437, "text": " "}, {"box": [427, 599, 473, 614], "id": 438, "text": "P"}, {"box": [427, 599, 473, 614], "id": 439, "text": "A"}, {"box": [427, 599, 473, 614], "id": 440, "text": "G"}, {"box": [427, 599, 473, 614], "id": 441, "text": "E"}, {"box": [427, 599, 473, 614], "id": 442, "text": "S"}, {"box": [427, 599, 473, 614], "id": 443, "text": " "}, {"box": [476, 601, 556, 615], "id": 444, "text": "P"}, {"box": [476, 601, 556, 615], "id": 445, "text": "R"}, {"box": [476, 601, 556, 615], "id": 446, "text": "O"}, {"box": [476, 601, 556, 615], "id": 447, "text": "P"}, {"box": [476, 601, 556, 615], "id": 448, "text": "E"}, {"box": [476, 601, 556, 615], "id": 449, "text": "R"}, {"box": [476, 601, 556, 615], "id": 450, "text": "L"}, {"box": [476, 601, 556, 615], "id": 451, "text": "Y"}, {"box": [476, 601, 556, 615], "id": 452, "text": ","}, {"box": [476, 601, 556, 615], "id": 453, "text": " "}, {"box": [274, 616, 330, 630], "id": 454, "text": "P"}, {"box": [274, 616, 330, 630], "id": 455, "text": "L"}, {"box": [274, 616, 330, 630], "id": 456, "text": "E"}, {"box": [274, 616, 330, 630], "id": 457, "text": "A"}, {"box": [274, 616, 330, 630], "id": 458, "text": "S"}, {"box": [274, 616, 330, 630], "id": 459, "text": "E"}, {"box": [274, 616, 330, 630], "id": 460, "text": " "}, {"box": [331, 616, 397, 630], "id": 461, "text": "C"}, {"box": [331, 616, 397, 630], "id": 462, "text": "O"}, {"box": [331, 616, 397, 630], "id": 463, "text": "N"}, {"box": [331, 616, 397, 630], "id": 464, "text": "T"}, {"box": [331, 616, 397, 630], "id": 465, "text": "A"}, {"box": [331, 616, 397, 630], "id": 466, "text": "C"}, {"box": [331, 616, 397, 630], "id": 467, "text": "T"}, {"box": [331, 616, 397, 630], "id": 468, "text": " "}, {"box": [399, 615, 453, 632], "id": 469, "text": "S"}, {"box": [399, 615, 453, 632], "id": 470, "text": "E"}, {"box": [399, 615, 453, 632], "id": 471, "text": "N"}, {"box": [399, 615, 453, 632], "id": 472, "text": "D"}, {"box": [399, 615, 453, 632], "id": 473, "text": "E"}, {"box": [399, 615, 453, 632], "id": 474, "text": "R"}, {"box": [399, 615, 453, 632], "id": 475, "text": " "}, {"box": [291, 631, 309, 644], "id": 476, "text": "A"}, {"box": [291, 631, 309, 644], "id": 477, "text": "S"}, {"box": [291, 631, 309, 644], "id": 478, "text": " "}, {"box": [311, 631, 349, 645], "id": 479, "text": "S"}, {"box": [311, 631, 349, 645], "id": 480, "text": "O"}, {"box": [311, 631, 349, 645], "id": 481, "text": "O"}, {"box": [311, 631, 349, 645], "id": 482, "text": "N"}, {"box": [311, 631, 349, 645], "id": 483, "text": " "}, {"box": [352, 633, 370, 646], "id": 484, "text": "A"}, {"box": [352, 633, 370, 646], "id": 485, "text": "S"}, {"box": [352, 633, 370, 646], "id": 486, "text": " "}, {"box": [373, 631, 439, 646], "id": 487, "text": "P"}, {"box": [373, 631, 439, 646], "id": 488, "text": "O"}, {"box": [373, 631, 439, 646], "id": 489, "text": "S"}, {"box": [373, 631, 439, 646], "id": 490, "text": "S"}, {"box": [373, 631, 439, 646], "id": 491, "text": "I"}, {"box": [373, 631, 439, 646], "id": 492, "text": "B"}, {"box": [373, 631, 439, 646], "id": 493, "text": "L"}, {"box": [373, 631, 439, 646], "id": 494, "text": "E"}]}, {"box": [162, 691, 626, 813], "text": "THIS MESSAGE IS INTENDED ONLY FOR THE USE OF THE INDIVIDUAL OR ENTITY TO WHOM IT IS ADDRESSED AND MAY CONTAIN INFORMATION THAT IS PRIVILEGED. CONFIDENTIAL, AND EXEMPT FROM DISCLOSURE UNDER APPLICABLE LAW. If the reader of this message is not the intended recipient of the employee or agent responsible for delivering the message to the intended recipient, you are hereby notified that any dissemination, distribution, copying, or conveying of this communication in any manner is strictly prohibited. If you have received this comunication in error, please notify us immediately by telephone and return the original message to us at the address below via the U. S. Postal Service. Thank you for your cooperation.", "id": 24, "words": [{"box": [163, 691, 190, 704], "id": 496, "text": "T"}, {"box": [163, 691, 190, 704], "id": 497, "text": "H"}, {"box": [163, 691, 190, 704], "id": 498, "text": "I"}, {"box": [163, 691, 190, 704], "id": 499, "text": "S"}, {"box": [163, 691, 190, 704], "id": 500, "text": " "}, {"box": [193, 691, 245, 705], "id": 501, "text": "M"}, {"box": [193, 691, 245, 705], "id": 502, "text": "E"}, {"box": [193, 691, 245, 705], "id": 503, "text": "S"}, {"box": [193, 691, 245, 705], "id": 504, "text": "S"}, {"box": [193, 691, 245, 705], "id": 505, "text": "A"}, {"box": [193, 691, 245, 705], "id": 506, "text": "G"}, {"box": [193, 691, 245, 705], "id": 507, "text": "E"}, {"box": [193, 691, 245, 705], "id": 508, "text": " "}, {"box": [249, 693, 260, 704], "id": 509, "text": "I"}, {"box": [249, 693, 260, 704], "id": 510, "text": "S"}, {"box": [249, 693, 260, 704], "id": 511, "text": " "}, {"box": [263, 694, 322, 705], "id": 512, "text": "I"}, {"box": [263, 694, 322, 705], "id": 513, "text": "N"}, {"box": [263, 694, 322, 705], "id": 514, "text": "T"}, {"box": [263, 694, 322, 705], "id": 515, "text": "E"}, {"box": [263, 694, 322, 705], "id": 516, "text": "N"}, {"box": [263, 694, 322, 705], "id": 517, "text": "D"}, {"box": [263, 694, 322, 705], "id": 518, "text": "E"}, {"box": [263, 694, 322, 705], "id": 519, "text": "D"}, {"box": [263, 694, 322, 705], "id": 520, "text": " "}, {"box": [323, 691, 354, 704], "id": 521, "text": "O"}, {"box": [323, 691, 354, 704], "id": 522, "text": "N"}, {"box": [323, 691, 354, 704], "id": 523, "text": "L"}, {"box": [323, 691, 354, 704], "id": 524, "text": "Y"}, {"box": [323, 691, 354, 704], "id": 525, "text": " "}, {"box": [356, 693, 378, 706], "id": 526, "text": "F"}, {"box": [356, 693, 378, 706], "id": 527, "text": "O"}, {"box": [356, 693, 378, 706], "id": 528, "text": "R"}, {"box": [356, 693, 378, 706], "id": 529, "text": " "}, {"box": [381, 693, 405, 704], "id": 530, "text": "T"}, {"box": [381, 693, 405, 704], "id": 531, "text": "H"}, {"box": [381, 693, 405, 704], "id": 532, "text": "E"}, {"box": [381, 693, 405, 704], "id": 533, "text": " "}, {"box": [408, 693, 428, 704], "id": 534, "text": "U"}, {"box": [408, 693, 428, 704], "id": 535, "text": "S"}, {"box": [408, 693, 428, 704], "id": 536, "text": "E"}, {"box": [408, 693, 428, 704], "id": 537, "text": " "}, {"box": [432, 693, 447, 704], "id": 538, "text": "O"}, {"box": [432, 693, 447, 704], "id": 539, "text": "F"}, {"box": [432, 693, 447, 704], "id": 540, "text": " "}, {"box": [450, 693, 472, 704], "id": 541, "text": "T"}, {"box": [450, 693, 472, 704], "id": 542, "text": "H"}, {"box": [450, 693, 472, 704], "id": 543, "text": "E"}, {"box": [450, 693, 472, 704], "id": 544, "text": " "}, {"box": [473, 691, 540, 705], "id": 545, "text": "I"}, {"box": [473, 691, 540, 705], "id": 546, "text": "N"}, {"box": [473, 691, 540, 705], "id": 547, "text": "D"}, {"box": [473, 691, 540, 705], "id": 548, "text": "I"}, {"box": [473, 691, 540, 705], "id": 549, "text": "V"}, {"box": [473, 691, 540, 705], "id": 550, "text": "I"}, {"box": [473, 691, 540, 705], "id": 551, "text": "D"}, {"box": [473, 691, 540, 705], "id": 552, "text": "U"}, {"box": [473, 691, 540, 705], "id": 553, "text": "A"}, {"box": [473, 691, 540, 705], "id": 554, "text": "L"}, {"box": [473, 691, 540, 705], "id": 555, "text": " "}, {"box": [546, 693, 561, 706], "id": 556, "text": "O"}, {"box": [546, 693, 561, 706], "id": 557, "text": "R"}, {"box": [546, 693, 561, 706], "id": 558, "text": " "}, {"box": [564, 693, 605, 704], "id": 559, "text": "E"}, {"box": [564, 693, 605, 704], "id": 560, "text": "N"}, {"box": [564, 693, 605, 704], "id": 561, "text": "T"}, {"box": [564, 693, 605, 704], "id": 562, "text": "I"}, {"box": [564, 693, 605, 704], "id": 563, "text": "T"}, {"box": [564, 693, 605, 704], "id": 564, "text": "Y"}, {"box": [564, 693, 605, 704], "id": 565, "text": " "}, {"box": [609, 694, 624, 704], "id": 566, "text": "T"}, {"box": [609, 694, 624, 704], "id": 567, "text": "O"}, {"box": [609, 694, 624, 704], "id": 568, "text": " "}, {"box": [163, 705, 201, 716], "id": 569, "text": "W"}, {"box": [163, 705, 201, 716], "id": 570, "text": "H"}, {"box": [163, 705, 201, 716], "id": 571, "text": "O"}, {"box": [163, 705, 201, 716], "id": 572, "text": "M"}, {"box": [163, 705, 201, 716], "id": 573, "text": " "}, {"box": [204, 707, 218, 717], "id": 574, "text": "I"}, {"box": [204, 707, 218, 717], "id": 575, "text": "T"}, {"box": [204, 707, 218, 717], "id": 576, "text": " "}, {"box": [222, 707, 235, 718], "id": 577, "text": "I"}, {"box": [222, 707, 235, 718], "id": 578, "text": "S"}, {"box": [222, 707, 235, 718], "id": 579, "text": " "}, {"box": [237, 707, 303, 718], "id": 580, "text": "A"}, {"box": [237, 707, 303, 718], "id": 581, "text": "D"}, {"box": [237, 707, 303, 718], "id": 582, "text": "D"}, {"box": [237, 707, 303, 718], "id": 583, "text": "R"}, {"box": [237, 707, 303, 718], "id": 584, "text": "E"}, {"box": [237, 707, 303, 718], "id": 585, "text": "S"}, {"box": [237, 707, 303, 718], "id": 586, "text": "S"}, {"box": [237, 707, 303, 718], "id": 587, "text": "E"}, {"box": [237, 707, 303, 718], "id": 588, "text": "D"}, {"box": [237, 707, 303, 718], "id": 589, "text": " "}, {"box": [307, 707, 334, 717], "id": 590, "text": "A"}, {"box": [307, 707, 334, 717], "id": 591, "text": "N"}, {"box": [307, 707, 334, 717], "id": 592, "text": "D"}, {"box": [307, 707, 334, 717], "id": 593, "text": " "}, {"box": [337, 707, 364, 718], "id": 594, "text": "M"}, {"box": [337, 707, 364, 718], "id": 595, "text": "A"}, {"box": [337, 707, 364, 718], "id": 596, "text": "Y"}, {"box": [337, 707, 364, 718], "id": 597, "text": " "}, {"box": [369, 707, 419, 718], "id": 598, "text": "C"}, {"box": [369, 707, 419, 718], "id": 599, "text": "O"}, {"box": [369, 707, 419, 718], "id": 600, "text": "N"}, {"box": [369, 707, 419, 718], "id": 601, "text": "T"}, {"box": [369, 707, 419, 718], "id": 602, "text": "A"}, {"box": [369, 707, 419, 718], "id": 603, "text": "I"}, {"box": [369, 707, 419, 718], "id": 604, "text": "N"}, {"box": [369, 707, 419, 718], "id": 605, "text": " "}, {"box": [422, 705, 500, 719], "id": 606, "text": "I"}, {"box": [422, 705, 500, 719], "id": 607, "text": "N"}, {"box": [422, 705, 500, 719], "id": 608, "text": "F"}, {"box": [422, 705, 500, 719], "id": 609, "text": "O"}, {"box": [422, 705, 500, 719], "id": 610, "text": "R"}, {"box": [422, 705, 500, 719], "id": 611, "text": "M"}, {"box": [422, 705, 500, 719], "id": 612, "text": "A"}, {"box": [422, 705, 500, 719], "id": 613, "text": "T"}, {"box": [422, 705, 500, 719], "id": 614, "text": "I"}, {"box": [422, 705, 500, 719], "id": 615, "text": "O"}, {"box": [422, 705, 500, 719], "id": 616, "text": "N"}, {"box": [422, 705, 500, 719], "id": 617, "text": " "}, {"box": [506, 705, 537, 718], "id": 618, "text": "T"}, {"box": [506, 705, 537, 718], "id": 619, "text": "H"}, {"box": [506, 705, 537, 718], "id": 620, "text": "A"}, {"box": [506, 705, 537, 718], "id": 621, "text": "T"}, {"box": [506, 705, 537, 718], "id": 622, "text": " "}, {"box": [541, 707, 551, 718], "id": 623, "text": "I"}, {"box": [541, 707, 551, 718], "id": 624, "text": "S"}, {"box": [541, 707, 551, 718], "id": 625, "text": " "}, {"box": [553, 707, 623, 720], "id": 626, "text": "P"}, {"box": [553, 707, 623, 720], "id": 627, "text": "R"}, {"box": [553, 707, 623, 720], "id": 628, "text": "I"}, {"box": [553, 707, 623, 720], "id": 629, "text": "V"}, {"box": [553, 707, 623, 720], "id": 630, "text": "I"}, {"box": [553, 707, 623, 720], "id": 631, "text": "L"}, {"box": [553, 707, 623, 720], "id": 632, "text": "E"}, {"box": [553, 707, 623, 720], "id": 633, "text": "G"}, {"box": [553, 707, 623, 720], "id": 634, "text": "E"}, {"box": [553, 707, 623, 720], "id": 635, "text": "D"}, {"box": [553, 707, 623, 720], "id": 636, "text": "."}, {"box": [553, 707, 623, 720], "id": 637, "text": " "}, {"box": [162, 718, 250, 732], "id": 638, "text": "C"}, {"box": [162, 718, 250, 732], "id": 639, "text": "O"}, {"box": [162, 718, 250, 732], "id": 640, "text": "N"}, {"box": [162, 718, 250, 732], "id": 641, "text": "F"}, {"box": [162, 718, 250, 732], "id": 642, "text": "I"}, {"box": [162, 718, 250, 732], "id": 643, "text": "D"}, {"box": [162, 718, 250, 732], "id": 644, "text": "E"}, {"box": [162, 718, 250, 732], "id": 645, "text": "N"}, {"box": [162, 718, 250, 732], "id": 646, "text": "T"}, {"box": [162, 718, 250, 732], "id": 647, "text": "I"}, {"box": [162, 718, 250, 732], "id": 648, "text": "A"}, {"box": [162, 718, 250, 732], "id": 649, "text": "L"}, {"box": [162, 718, 250, 732], "id": 650, "text": ","}, {"box": [162, 718, 250, 732], "id": 651, "text": " "}, {"box": [254, 721, 281, 732], "id": 652, "text": "A"}, {"box": [254, 721, 281, 732], "id": 653, "text": "N"}, {"box": [254, 721, 281, 732], "id": 654, "text": "D"}, {"box": [254, 721, 281, 732], "id": 655, "text": " "}, {"box": [284, 721, 330, 732], "id": 656, "text": "E"}, {"box": [284, 721, 330, 732], "id": 657, "text": "X"}, {"box": [284, 721, 330, 732], "id": 658, "text": "E"}, {"box": [284, 721, 330, 732], "id": 659, "text": "M"}, {"box": [284, 721, 330, 732], "id": 660, "text": "P"}, {"box": [284, 721, 330, 732], "id": 661, "text": "T"}, {"box": [284, 721, 330, 732], "id": 662, "text": " "}, {"box": [332, 721, 366, 731], "id": 663, "text": "F"}, {"box": [332, 721, 366, 731], "id": 664, "text": "R"}, {"box": [332, 721, 366, 731], "id": 665, "text": "O"}, {"box": [332, 721, 366, 731], "id": 666, "text": "M"}, {"box": [332, 721, 366, 731], "id": 667, "text": " "}, {"box": [369, 721, 439, 732], "id": 668, "text": "D"}, {"box": [369, 721, 439, 732], "id": 669, "text": "I"}, {"box": [369, 721, 439, 732], "id": 670, "text": "S"}, {"box": [369, 721, 439, 732], "id": 671, "text": "C"}, {"box": [369, 721, 439, 732], "id": 672, "text": "L"}, {"box": [369, 721, 439, 732], "id": 673, "text": "O"}, {"box": [369, 721, 439, 732], "id": 674, "text": "S"}, {"box": [369, 721, 439, 732], "id": 675, "text": "U"}, {"box": [369, 721, 439, 732], "id": 676, "text": "R"}, {"box": [369, 721, 439, 732], "id": 677, "text": "E"}, {"box": [369, 721, 439, 732], "id": 678, "text": " "}, {"box": [441, 719, 480, 730], "id": 679, "text": "U"}, {"box": [441, 719, 480, 730], "id": 680, "text": "N"}, {"box": [441, 719, 480, 730], "id": 681, "text": "D"}, {"box": [441, 719, 480, 730], "id": 682, "text": "E"}, {"box": [441, 719, 480, 730], "id": 683, "text": "R"}, {"box": [441, 719, 480, 730], "id": 684, "text": " "}, {"box": [483, 721, 554, 732], "id": 685, "text": "A"}, {"box": [483, 721, 554, 732], "id": 686, "text": "P"}, {"box": [483, 721, 554, 732], "id": 687, "text": "P"}, {"box": [483, 721, 554, 732], "id": 688, "text": "L"}, {"box": [483, 721, 554, 732], "id": 689, "text": "I"}, {"box": [483, 721, 554, 732], "id": 690, "text": "C"}, {"box": [483, 721, 554, 732], "id": 691, "text": "A"}, {"box": [483, 721, 554, 732], "id": 692, "text": "B"}, {"box": [483, 721, 554, 732], "id": 693, "text": "L"}, {"box": [483, 721, 554, 732], "id": 694, "text": "E"}, {"box": [483, 721, 554, 732], "id": 695, "text": " "}, {"box": [557, 721, 586, 732], "id": 696, "text": "L"}, {"box": [557, 721, 586, 732], "id": 697, "text": "A"}, {"box": [557, 721, 586, 732], "id": 698, "text": "W"}, {"box": [557, 721, 586, 732], "id": 699, "text": "."}, {"box": [557, 721, 586, 732], "id": 700, "text": " "}, {"box": [594, 722, 607, 732], "id": 701, "text": "I"}, {"box": [594, 722, 607, 732], "id": 702, "text": "f"}, {"box": [594, 722, 607, 732], "id": 703, "text": " "}, {"box": [610, 721, 624, 731], "id": 704, "text": "t"}, {"box": [610, 721, 624, 731], "id": 705, "text": "h"}, {"box": [610, 721, 624, 731], "id": 706, "text": "e"}, {"box": [610, 721, 624, 731], "id": 707, "text": " "}, {"box": [163, 733, 192, 744], "id": 708, "text": "r"}, {"box": [163, 733, 192, 744], "id": 709, "text": "e"}, {"box": [163, 733, 192, 744], "id": 710, "text": "a"}, {"box": [163, 733, 192, 744], "id": 711, "text": "d"}, {"box": [163, 733, 192, 744], "id": 712, "text": "e"}, {"box": [163, 733, 192, 744], "id": 713, "text": "r"}, {"box": [163, 733, 192, 744], "id": 714, "text": " "}, {"box": [196, 735, 207, 745], "id": 715, "text": "o"}, {"box": [196, 735, 207, 745], "id": 716, "text": "f"}, {"box": [196, 735, 207, 745], "id": 717, "text": " "}, {"box": [207, 733, 225, 746], "id": 718, "text": "t"}, {"box": [207, 733, 225, 746], "id": 719, "text": "h"}, {"box": [207, 733, 225, 746], "id": 720, "text": "i"}, {"box": [207, 733, 225, 746], "id": 721, "text": "s"}, {"box": [207, 733, 225, 746], "id": 722, "text": " "}, {"box": [226, 735, 264, 746], "id": 723, "text": "m"}, {"box": [226, 735, 264, 746], "id": 724, "text": "e"}, {"box": [226, 735, 264, 746], "id": 725, "text": "s"}, {"box": [226, 735, 264, 746], "id": 726, "text": "s"}, {"box": [226, 735, 264, 746], "id": 727, "text": "a"}, {"box": [226, 735, 264, 746], "id": 728, "text": "g"}, {"box": [226, 735, 264, 746], "id": 729, "text": "e"}, {"box": [226, 735, 264, 746], "id": 730, "text": " "}, {"box": [267, 735, 275, 743], "id": 731, "text": "i"}, {"box": [267, 735, 275, 743], "id": 732, "text": "s"}, {"box": [267, 735, 275, 743], "id": 733, "text": " "}, {"box": [277, 736, 294, 744], "id": 734, "text": "n"}, {"box": [277, 736, 294, 744], "id": 735, "text": "o"}, {"box": [277, 736, 294, 744], "id": 736, "text": "t"}, {"box": [277, 736, 294, 744], "id": 737, "text": " "}, {"box": [293, 733, 308, 744], "id": 738, "text": "t"}, {"box": [293, 733, 308, 744], "id": 739, "text": "h"}, {"box": [293, 733, 308, 744], "id": 740, "text": "e"}, {"box": [293, 733, 308, 744], "id": 741, "text": " "}, {"box": [310, 735, 349, 746], "id": 742, "text": "i"}, {"box": [310, 735, 349, 746], "id": 743, "text": "n"}, {"box": [310, 735, 349, 746], "id": 744, "text": "t"}, {"box": [310, 735, 349, 746], "id": 745, "text": "e"}, {"box": [310, 735, 349, 746], "id": 746, "text": "n"}, {"box": [310, 735, 349, 746], "id": 747, "text": "d"}, {"box": [310, 735, 349, 746], "id": 748, "text": "e"}, {"box": [310, 735, 349, 746], "id": 749, "text": "d"}, {"box": [310, 735, 349, 746], "id": 750, "text": " "}, {"box": [352, 735, 391, 748], "id": 751, "text": "r"}, {"box": [352, 735, 391, 748], "id": 752, "text": "e"}, {"box": [352, 735, 391, 748], "id": 753, "text": "c"}, {"box": [352, 735, 391, 748], "id": 754, "text": "i"}, {"box": [352, 735, 391, 748], "id": 755, "text": "p"}, {"box": [352, 735, 391, 748], "id": 756, "text": "i"}, {"box": [352, 735, 391, 748], "id": 757, "text": "e"}, {"box": [352, 735, 391, 748], "id": 758, "text": "n"}, {"box": [352, 735, 391, 748], "id": 759, "text": "t"}, {"box": [352, 735, 391, 748], "id": 760, "text": " "}, {"box": [394, 735, 404, 745], "id": 761, "text": "o"}, {"box": [394, 735, 404, 745], "id": 762, "text": "f"}, {"box": [394, 735, 404, 745], "id": 763, "text": " "}, {"box": [405, 735, 420, 745], "id": 764, "text": "t"}, {"box": [405, 735, 420, 745], "id": 765, "text": "h"}, {"box": [405, 735, 420, 745], "id": 766, "text": "e"}, {"box": [405, 735, 420, 745], "id": 767, "text": " "}, {"box": [422, 735, 465, 748], "id": 768, "text": "e"}, {"box": [422, 735, 465, 748], "id": 769, "text": "m"}, {"box": [422, 735, 465, 748], "id": 770, "text": "p"}, {"box": [422, 735, 465, 748], "id": 771, "text": "l"}, {"box": [422, 735, 465, 748], "id": 772, "text": "o"}, {"box": [422, 735, 465, 748], "id": 773, "text": "y"}, {"box": [422, 735, 465, 748], "id": 774, "text": "e"}, {"box": [422, 735, 465, 748], "id": 775, "text": "e"}, {"box": [422, 735, 465, 748], "id": 776, "text": " "}, {"box": [468, 736, 479, 744], "id": 777, "text": "o"}, {"box": [468, 736, 479, 744], "id": 778, "text": "r"}, {"box": [468, 736, 479, 744], "id": 779, "text": " "}, {"box": [479, 736, 506, 747], "id": 780, "text": "a"}, {"box": [479, 736, 506, 747], "id": 781, "text": "g"}, {"box": [479, 736, 506, 747], "id": 782, "text": "e"}, {"box": [479, 736, 506, 747], "id": 783, "text": "n"}, {"box": [479, 736, 506, 747], "id": 784, "text": "t"}, {"box": [479, 736, 506, 747], "id": 785, "text": " "}, {"box": [507, 735, 559, 746], "id": 786, "text": "r"}, {"box": [507, 735, 559, 746], "id": 787, "text": "e"}, {"box": [507, 735, 559, 746], "id": 788, "text": "s"}, {"box": [507, 735, 559, 746], "id": 789, "text": "p"}, {"box": [507, 735, 559, 746], "id": 790, "text": "o"}, {"box": [507, 735, 559, 746], "id": 791, "text": "n"}, {"box": [507, 735, 559, 746], "id": 792, "text": "s"}, {"box": [507, 735, 559, 746], "id": 793, "text": "i"}, {"box": [507, 735, 559, 746], "id": 794, "text": "b"}, {"box": [507, 735, 559, 746], "id": 795, "text": "l"}, {"box": [507, 735, 559, 746], "id": 796, "text": "e"}, {"box": [507, 735, 559, 746], "id": 797, "text": " "}, {"box": [561, 736, 576, 744], "id": 798, "text": "f"}, {"box": [561, 736, 576, 744], "id": 799, "text": "o"}, {"box": [561, 736, 576, 744], "id": 800, "text": "r"}, {"box": [561, 736, 576, 744], "id": 801, "text": " "}, {"box": [580, 735, 626, 748], "id": 802, "text": "d"}, {"box": [580, 735, 626, 748], "id": 803, "text": "e"}, {"box": [580, 735, 626, 748], "id": 804, "text": "l"}, {"box": [580, 735, 626, 748], "id": 805, "text": "i"}, {"box": [580, 735, 626, 748], "id": 806, "text": "v"}, {"box": [580, 735, 626, 748], "id": 807, "text": "e"}, {"box": [580, 735, 626, 748], "id": 808, "text": "r"}, {"box": [580, 735, 626, 748], "id": 809, "text": "i"}, {"box": [580, 735, 626, 748], "id": 810, "text": "n"}, {"box": [580, 735, 626, 748], "id": 811, "text": "g"}, {"box": [580, 735, 626, 748], "id": 812, "text": " "}, {"box": [163, 746, 178, 759], "id": 813, "text": "t"}, {"box": [163, 746, 178, 759], "id": 814, "text": "h"}, {"box": [163, 746, 178, 759], "id": 815, "text": "e"}, {"box": [163, 746, 178, 759], "id": 816, "text": " "}, {"box": [182, 747, 221, 760], "id": 817, "text": "m"}, {"box": [182, 747, 221, 760], "id": 818, "text": "e"}, {"box": [182, 747, 221, 760], "id": 819, "text": "s"}, {"box": [182, 747, 221, 760], "id": 820, "text": "s"}, {"box": [182, 747, 221, 760], "id": 821, "text": "a"}, {"box": [182, 747, 221, 760], "id": 822, "text": "g"}, {"box": [182, 747, 221, 760], "id": 823, "text": "e"}, {"box": [182, 747, 221, 760], "id": 824, "text": " "}, {"box": [225, 749, 236, 757], "id": 825, "text": "t"}, {"box": [225, 749, 236, 757], "id": 826, "text": "o"}, {"box": [225, 749, 236, 757], "id": 827, "text": " "}, {"box": [239, 747, 253, 757], "id": 828, "text": "t"}, {"box": [239, 747, 253, 757], "id": 829, "text": "h"}, {"box": [239, 747, 253, 757], "id": 830, "text": "e"}, {"box": [239, 747, 253, 757], "id": 831, "text": " "}, {"box": [256, 747, 297, 757], "id": 832, "text": "i"}, {"box": [256, 747, 297, 757], "id": 833, "text": "n"}, {"box": [256, 747, 297, 757], "id": 834, "text": "t"}, {"box": [256, 747, 297, 757], "id": 835, "text": "e"}, {"box": [256, 747, 297, 757], "id": 836, "text": "n"}, {"box": [256, 747, 297, 757], "id": 837, "text": "d"}, {"box": [256, 747, 297, 757], "id": 838, "text": "e"}, {"box": [256, 747, 297, 757], "id": 839, "text": "d"}, {"box": [256, 747, 297, 757], "id": 840, "text": " "}, {"box": [299, 747, 341, 758], "id": 841, "text": "r"}, {"box": [299, 747, 341, 758], "id": 842, "text": "e"}, {"box": [299, 747, 341, 758], "id": 843, "text": "c"}, {"box": [299, 747, 341, 758], "id": 844, "text": "i"}, {"box": [299, 747, 341, 758], "id": 845, "text": "p"}, {"box": [299, 747, 341, 758], "id": 846, "text": "i"}, {"box": [299, 747, 341, 758], "id": 847, "text": "e"}, {"box": [299, 747, 341, 758], "id": 848, "text": "n"}, {"box": [299, 747, 341, 758], "id": 849, "text": "t"}, {"box": [299, 747, 341, 758], "id": 850, "text": ","}, {"box": [299, 747, 341, 758], "id": 851, "text": " "}, {"box": [345, 749, 363, 760], "id": 852, "text": "y"}, {"box": [345, 749, 363, 760], "id": 853, "text": "o"}, {"box": [345, 749, 363, 760], "id": 854, "text": "u"}, {"box": [345, 749, 363, 760], "id": 855, "text": " "}, {"box": [366, 749, 379, 759], "id": 856, "text": "a"}, {"box": [366, 749, 379, 759], "id": 857, "text": "r"}, {"box": [366, 749, 379, 759], "id": 858, "text": "e"}, {"box": [366, 749, 379, 759], "id": 859, "text": " "}, {"box": [384, 747, 416, 758], "id": 860, "text": "h"}, {"box": [384, 747, 416, 758], "id": 861, "text": "e"}, {"box": [384, 747, 416, 758], "id": 862, "text": "r"}, {"box": [384, 747, 416, 758], "id": 863, "text": "e"}, {"box": [384, 747, 416, 758], "id": 864, "text": "b"}, {"box": [384, 747, 416, 758], "id": 865, "text": "y"}, {"box": [384, 747, 416, 758], "id": 866, "text": " "}, {"box": [419, 747, 455, 757], "id": 867, "text": "n"}, {"box": [419, 747, 455, 757], "id": 868, "text": "o"}, {"box": [419, 747, 455, 757], "id": 869, "text": "t"}, {"box": [419, 747, 455, 757], "id": 870, "text": "i"}, {"box": [419, 747, 455, 757], "id": 871, "text": "f"}, {"box": [419, 747, 455, 757], "id": 872, "text": "i"}, {"box": [419, 747, 455, 757], "id": 873, "text": "e"}, {"box": [419, 747, 455, 757], "id": 874, "text": "d"}, {"box": [419, 747, 455, 757], "id": 875, "text": " "}, {"box": [457, 747, 477, 758], "id": 876, "text": "t"}, {"box": [457, 747, 477, 758], "id": 877, "text": "h"}, {"box": [457, 747, 477, 758], "id": 878, "text": "a"}, {"box": [457, 747, 477, 758], "id": 879, "text": "t"}, {"box": [457, 747, 477, 758], "id": 880, "text": " "}, {"box": [479, 749, 497, 759], "id": 881, "text": "a"}, {"box": [479, 749, 497, 759], "id": 882, "text": "n"}, {"box": [479, 749, 497, 759], "id": 883, "text": "y"}, {"box": [479, 749, 497, 759], "id": 884, "text": " "}, {"box": [500, 749, 567, 760], "id": 885, "text": "d"}, {"box": [500, 749, 567, 760], "id": 886, "text": "i"}, {"box": [500, 749, 567, 760], "id": 887, "text": "s"}, {"box": [500, 749, 567, 760], "id": 888, "text": "s"}, {"box": [500, 749, 567, 760], "id": 889, "text": "e"}, {"box": [500, 749, 567, 760], "id": 890, "text": "m"}, {"box": [500, 749, 567, 760], "id": 891, "text": "i"}, {"box": [500, 749, 567, 760], "id": 892, "text": "n"}, {"box": [500, 749, 567, 760], "id": 893, "text": "a"}, {"box": [500, 749, 567, 760], "id": 894, "text": "t"}, {"box": [500, 749, 567, 760], "id": 895, "text": "i"}, {"box": [500, 749, 567, 760], "id": 896, "text": "o"}, {"box": [500, 749, 567, 760], "id": 897, "text": "n"}, {"box": [500, 749, 567, 760], "id": 898, "text": ","}, {"box": [500, 749, 567, 760], "id": 899, "text": " "}, {"box": [570, 747, 624, 758], "id": 900, "text": "d"}, {"box": [570, 747, 624, 758], "id": 901, "text": "i"}, {"box": [570, 747, 624, 758], "id": 902, "text": "s"}, {"box": [570, 747, 624, 758], "id": 903, "text": "t"}, {"box": [570, 747, 624, 758], "id": 904, "text": "r"}, {"box": [570, 747, 624, 758], "id": 905, "text": "i"}, {"box": [570, 747, 624, 758], "id": 906, "text": "b"}, {"box": [570, 747, 624, 758], "id": 907, "text": "u"}, {"box": [570, 747, 624, 758], "id": 908, "text": "t"}, {"box": [570, 747, 624, 758], "id": 909, "text": "i"}, {"box": [570, 747, 624, 758], "id": 910, "text": "o"}, {"box": [570, 747, 624, 758], "id": 911, "text": "n"}, {"box": [570, 747, 624, 758], "id": 912, "text": ","}, {"box": [570, 747, 624, 758], "id": 913, "text": " "}, {"box": [163, 761, 204, 772], "id": 914, "text": "c"}, {"box": [163, 761, 204, 772], "id": 915, "text": "o"}, {"box": [163, 761, 204, 772], "id": 916, "text": "p"}, {"box": [163, 761, 204, 772], "id": 917, "text": "y"}, {"box": [163, 761, 204, 772], "id": 918, "text": "i"}, {"box": [163, 761, 204, 772], "id": 919, "text": "n"}, {"box": [163, 761, 204, 772], "id": 920, "text": "g"}, {"box": [163, 761, 204, 772], "id": 921, "text": ","}, {"box": [163, 761, 204, 772], "id": 922, "text": " "}, {"box": [208, 763, 219, 771], "id": 923, "text": "o"}, {"box": [208, 763, 219, 771], "id": 924, "text": "r"}, {"box": [208, 763, 219, 771], "id": 925, "text": " "}, {"box": [223, 761, 270, 772], "id": 926, "text": "c"}, {"box": [223, 761, 270, 772], "id": 927, "text": "o"}, {"box": [223, 761, 270, 772], "id": 928, "text": "n"}, {"box": [223, 761, 270, 772], "id": 929, "text": "v"}, {"box": [223, 761, 270, 772], "id": 930, "text": "e"}, {"box": [223, 761, 270, 772], "id": 931, "text": "y"}, {"box": [223, 761, 270, 772], "id": 932, "text": "i"}, {"box": [223, 761, 270, 772], "id": 933, "text": "n"}, {"box": [223, 761, 270, 772], "id": 934, "text": "g"}, {"box": [223, 761, 270, 772], "id": 935, "text": " "}, {"box": [275, 760, 286, 771], "id": 936, "text": "o"}, {"box": [275, 760, 286, 771], "id": 937, "text": "f"}, {"box": [275, 760, 286, 771], "id": 938, "text": " "}, {"box": [291, 760, 308, 771], "id": 939, "text": "t"}, {"box": [291, 760, 308, 771], "id": 940, "text": "h"}, {"box": [291, 760, 308, 771], "id": 941, "text": "i"}, {"box": [291, 760, 308, 771], "id": 942, "text": "s"}, {"box": [291, 760, 308, 771], "id": 943, "text": " "}, {"box": [310, 761, 381, 771], "id": 944, "text": "c"}, {"box": [310, 761, 381, 771], "id": 945, "text": "o"}, {"box": [310, 761, 381, 771], "id": 946, "text": "m"}, {"box": [310, 761, 381, 771], "id": 947, "text": "m"}, {"box": [310, 761, 381, 771], "id": 948, "text": "u"}, {"box": [310, 761, 381, 771], "id": 949, "text": "n"}, {"box": [310, 761, 381, 771], "id": 950, "text": "i"}, {"box": [310, 761, 381, 771], "id": 951, "text": "c"}, {"box": [310, 761, 381, 771], "id": 952, "text": "a"}, {"box": [310, 761, 381, 771], "id": 953, "text": "t"}, {"box": [310, 761, 381, 771], "id": 954, "text": "i"}, {"box": [310, 761, 381, 771], "id": 955, "text": "o"}, {"box": [310, 761, 381, 771], "id": 956, "text": "n"}, {"box": [310, 761, 381, 771], "id": 957, "text": " "}, {"box": [385, 760, 395, 771], "id": 958, "text": "i"}, {"box": [385, 760, 395, 771], "id": 959, "text": "n"}, {"box": [385, 760, 395, 771], "id": 960, "text": " "}, {"box": [398, 763, 416, 773], "id": 961, "text": "a"}, {"box": [398, 763, 416, 773], "id": 962, "text": "n"}, {"box": [398, 763, 416, 773], "id": 963, "text": "y"}, {"box": [398, 763, 416, 773], "id": 964, "text": " "}, {"box": [420, 763, 454, 773], "id": 965, "text": "m"}, {"box": [420, 763, 454, 773], "id": 966, "text": "a"}, {"box": [420, 763, 454, 773], "id": 967, "text": "n"}, {"box": [420, 763, 454, 773], "id": 968, "text": "n"}, {"box": [420, 763, 454, 773], "id": 969, "text": "e"}, {"box": [420, 763, 454, 773], "id": 970, "text": "r"}, {"box": [420, 763, 454, 773], "id": 971, "text": " "}, {"box": [458, 760, 468, 771], "id": 972, "text": "i"}, {"box": [458, 760, 468, 771], "id": 973, "text": "s"}, {"box": [458, 760, 468, 771], "id": 974, "text": " "}, {"box": [471, 761, 505, 772], "id": 975, "text": "s"}, {"box": [471, 761, 505, 772], "id": 976, "text": "t"}, {"box": [471, 761, 505, 772], "id": 977, "text": "r"}, {"box": [471, 761, 505, 772], "id": 978, "text": "i"}, {"box": [471, 761, 505, 772], "id": 979, "text": "c"}, {"box": [471, 761, 505, 772], "id": 980, "text": "t"}, {"box": [471, 761, 505, 772], "id": 981, "text": "l"}, {"box": [471, 761, 505, 772], "id": 982, "text": "y"}, {"box": [471, 761, 505, 772], "id": 983, "text": " "}, {"box": [506, 761, 556, 772], "id": 984, "text": "p"}, {"box": [506, 761, 556, 772], "id": 985, "text": "r"}, {"box": [506, 761, 556, 772], "id": 986, "text": "o"}, {"box": [506, 761, 556, 772], "id": 987, "text": "h"}, {"box": [506, 761, 556, 772], "id": 988, "text": "i"}, {"box": [506, 761, 556, 772], "id": 989, "text": "b"}, {"box": [506, 761, 556, 772], "id": 990, "text": "i"}, {"box": [506, 761, 556, 772], "id": 991, "text": "t"}, {"box": [506, 761, 556, 772], "id": 992, "text": "e"}, {"box": [506, 761, 556, 772], "id": 993, "text": "d"}, {"box": [506, 761, 556, 772], "id": 994, "text": "."}, {"box": [506, 761, 556, 772], "id": 995, "text": " "}, {"box": [566, 761, 579, 771], "id": 996, "text": "I"}, {"box": [566, 761, 579, 771], "id": 997, "text": "f"}, {"box": [566, 761, 579, 771], "id": 998, "text": " "}, {"box": [580, 761, 598, 772], "id": 999, "text": "y"}, {"box": [580, 761, 598, 772], "id": 1000, "text": "o"}, {"box": [580, 761, 598, 772], "id": 1001, "text": "u"}, {"box": [580, 761, 598, 772], "id": 1002, "text": " "}, {"box": [602, 761, 623, 772], "id": 1003, "text": "h"}, {"box": [602, 761, 623, 772], "id": 1004, "text": "a"}, {"box": [602, 761, 623, 772], "id": 1005, "text": "v"}, {"box": [602, 761, 623, 772], "id": 1006, "text": "e"}, {"box": [602, 761, 623, 772], "id": 1007, "text": " "}, {"box": [163, 774, 204, 785], "id": 1008, "text": "r"}, {"box": [163, 774, 204, 785], "id": 1009, "text": "e"}, {"box": [163, 774, 204, 785], "id": 1010, "text": "c"}, {"box": [163, 774, 204, 785], "id": 1011, "text": "e"}, {"box": [163, 774, 204, 785], "id": 1012, "text": "i"}, {"box": [163, 774, 204, 785], "id": 1013, "text": "v"}, {"box": [163, 774, 204, 785], "id": 1014, "text": "e"}, {"box": [163, 774, 204, 785], "id": 1015, "text": "d"}, {"box": [163, 774, 204, 785], "id": 1016, "text": " "}, {"box": [207, 774, 225, 784], "id": 1017, "text": "t"}, {"box": [207, 774, 225, 784], "id": 1018, "text": "h"}, {"box": [207, 774, 225, 784], "id": 1019, "text": "i"}, {"box": [207, 774, 225, 784], "id": 1020, "text": "s"}, {"box": [207, 774, 225, 784], "id": 1021, "text": " "}, {"box": [229, 772, 299, 786], "id": 1022, "text": "c"}, {"box": [229, 772, 299, 786], "id": 1023, "text": "o"}, {"box": [229, 772, 299, 786], "id": 1024, "text": "m"}, {"box": [229, 772, 299, 786], "id": 1025, "text": "u"}, {"box": [229, 772, 299, 786], "id": 1026, "text": "n"}, {"box": [229, 772, 299, 786], "id": 1027, "text": "i"}, {"box": [229, 772, 299, 786], "id": 1028, "text": "c"}, {"box": [229, 772, 299, 786], "id": 1029, "text": "a"}, {"box": [229, 772, 299, 786], "id": 1030, "text": "t"}, {"box": [229, 772, 299, 786], "id": 1031, "text": "i"}, {"box": [229, 772, 299, 786], "id": 1032, "text": "o"}, {"box": [229, 772, 299, 786], "id": 1033, "text": "n"}, {"box": [229, 772, 299, 786], "id": 1034, "text": " "}, {"box": [303, 774, 313, 784], "id": 1035, "text": "i"}, {"box": [303, 774, 313, 784], "id": 1036, "text": "n"}, {"box": [303, 774, 313, 784], "id": 1037, "text": " "}, {"box": [317, 775, 344, 785], "id": 1038, "text": "e"}, {"box": [317, 775, 344, 785], "id": 1039, "text": "r"}, {"box": [317, 775, 344, 785], "id": 1040, "text": "r"}, {"box": [317, 775, 344, 785], "id": 1041, "text": "o"}, {"box": [317, 775, 344, 785], "id": 1042, "text": "r"}, {"box": [317, 775, 344, 785], "id": 1043, "text": ","}, {"box": [317, 775, 344, 785], "id": 1044, "text": " "}, {"box": [346, 774, 377, 785], "id": 1045, "text": "p"}, {"box": [346, 774, 377, 785], "id": 1046, "text": "l"}, {"box": [346, 774, 377, 785], "id": 1047, "text": "e"}, {"box": [346, 774, 377, 785], "id": 1048, "text": "a"}, {"box": [346, 774, 377, 785], "id": 1049, "text": "s"}, {"box": [346, 774, 377, 785], "id": 1050, "text": "e"}, {"box": [346, 774, 377, 785], "id": 1051, "text": " "}, {"box": [381, 774, 408, 785], "id": 1052, "text": "n"}, {"box": [381, 774, 408, 785], "id": 1053, "text": "o"}, {"box": [381, 774, 408, 785], "id": 1054, "text": "t"}, {"box": [381, 774, 408, 785], "id": 1055, "text": "i"}, {"box": [381, 774, 408, 785], "id": 1056, "text": "f"}, {"box": [381, 774, 408, 785], "id": 1057, "text": "y"}, {"box": [381, 774, 408, 785], "id": 1058, "text": " "}, {"box": [413, 777, 423, 785], "id": 1059, "text": "u"}, {"box": [413, 777, 423, 785], "id": 1060, "text": "s"}, {"box": [413, 777, 423, 785], "id": 1061, "text": " "}, {"box": [429, 774, 485, 785], "id": 1062, "text": "i"}, {"box": [429, 774, 485, 785], "id": 1063, "text": "m"}, {"box": [429, 774, 485, 785], "id": 1064, "text": "m"}, {"box": [429, 774, 485, 785], "id": 1065, "text": "e"}, {"box": [429, 774, 485, 785], "id": 1066, "text": "d"}, {"box": [429, 774, 485, 785], "id": 1067, "text": "i"}, {"box": [429, 774, 485, 785], "id": 1068, "text": "a"}, {"box": [429, 774, 485, 785], "id": 1069, "text": "t"}, {"box": [429, 774, 485, 785], "id": 1070, "text": "e"}, {"box": [429, 774, 485, 785], "id": 1071, "text": "l"}, {"box": [429, 774, 485, 785], "id": 1072, "text": "y"}, {"box": [429, 774, 485, 785], "id": 1073, "text": " "}, {"box": [487, 774, 500, 785], "id": 1074, "text": "b"}, {"box": [487, 774, 500, 785], "id": 1075, "text": "y"}, {"box": [487, 774, 500, 785], "id": 1076, "text": " "}, {"box": [506, 774, 551, 787], "id": 1077, "text": "t"}, {"box": [506, 774, 551, 787], "id": 1078, "text": "e"}, {"box": [506, 774, 551, 787], "id": 1079, "text": "l"}, {"box": [506, 774, 551, 787], "id": 1080, "text": "e"}, {"box": [506, 774, 551, 787], "id": 1081, "text": "p"}, {"box": [506, 774, 551, 787], "id": 1082, "text": "h"}, {"box": [506, 774, 551, 787], "id": 1083, "text": "o"}, {"box": [506, 774, 551, 787], "id": 1084, "text": "n"}, {"box": [506, 774, 551, 787], "id": 1085, "text": "e"}, {"box": [506, 774, 551, 787], "id": 1086, "text": " "}, {"box": [553, 775, 573, 785], "id": 1087, "text": "a"}, {"box": [553, 775, 573, 785], "id": 1088, "text": "n"}, {"box": [553, 775, 573, 785], "id": 1089, "text": "d"}, {"box": [553, 775, 573, 785], "id": 1090, "text": " "}, {"box": [577, 775, 605, 785], "id": 1091, "text": "r"}, {"box": [577, 775, 605, 785], "id": 1092, "text": "e"}, {"box": [577, 775, 605, 785], "id": 1093, "text": "t"}, {"box": [577, 775, 605, 785], "id": 1094, "text": "u"}, {"box": [577, 775, 605, 785], "id": 1095, "text": "r"}, {"box": [577, 775, 605, 785], "id": 1096, "text": "n"}, {"box": [577, 775, 605, 785], "id": 1097, "text": " "}, {"box": [608, 774, 623, 784], "id": 1098, "text": "t"}, {"box": [608, 774, 623, 784], "id": 1099, "text": "h"}, {"box": [608, 774, 623, 784], "id": 1100, "text": "e"}, {"box": [608, 774, 623, 784], "id": 1101, "text": " "}, {"box": [162, 788, 201, 799], "id": 1102, "text": "o"}, {"box": [162, 788, 201, 799], "id": 1103, "text": "r"}, {"box": [162, 788, 201, 799], "id": 1104, "text": "i"}, {"box": [162, 788, 201, 799], "id": 1105, "text": "g"}, {"box": [162, 788, 201, 799], "id": 1106, "text": "i"}, {"box": [162, 788, 201, 799], "id": 1107, "text": "n"}, {"box": [162, 788, 201, 799], "id": 1108, "text": "a"}, {"box": [162, 788, 201, 799], "id": 1109, "text": "l"}, {"box": [162, 788, 201, 799], "id": 1110, "text": " "}, {"box": [204, 786, 243, 799], "id": 1111, "text": "m"}, {"box": [204, 786, 243, 799], "id": 1112, "text": "e"}, {"box": [204, 786, 243, 799], "id": 1113, "text": "s"}, {"box": [204, 786, 243, 799], "id": 1114, "text": "s"}, {"box": [204, 786, 243, 799], "id": 1115, "text": "a"}, {"box": [204, 786, 243, 799], "id": 1116, "text": "g"}, {"box": [204, 786, 243, 799], "id": 1117, "text": "e"}, {"box": [204, 786, 243, 799], "id": 1118, "text": " "}, {"box": [247, 788, 258, 798], "id": 1119, "text": "t"}, {"box": [247, 788, 258, 798], "id": 1120, "text": "o"}, {"box": [247, 788, 258, 798], "id": 1121, "text": " "}, {"box": [263, 789, 274, 797], "id": 1122, "text": "u"}, {"box": [263, 789, 274, 797], "id": 1123, "text": "s"}, {"box": [263, 789, 274, 797], "id": 1124, "text": " "}, {"box": [279, 788, 287, 798], "id": 1125, "text": "a"}, {"box": [279, 788, 287, 798], "id": 1126, "text": "t"}, {"box": [279, 788, 287, 798], "id": 1127, "text": " "}, {"box": [291, 788, 306, 798], "id": 1128, "text": "t"}, {"box": [291, 788, 306, 798], "id": 1129, "text": "h"}, {"box": [291, 788, 306, 798], "id": 1130, "text": "e"}, {"box": [291, 788, 306, 798], "id": 1131, "text": " "}, {"box": [311, 788, 346, 799], "id": 1132, "text": "a"}, {"box": [311, 788, 346, 799], "id": 1133, "text": "d"}, {"box": [311, 788, 346, 799], "id": 1134, "text": "d"}, {"box": [311, 788, 346, 799], "id": 1135, "text": "r"}, {"box": [311, 788, 346, 799], "id": 1136, "text": "e"}, {"box": [311, 788, 346, 799], "id": 1137, "text": "s"}, {"box": [311, 788, 346, 799], "id": 1138, "text": "s"}, {"box": [311, 788, 346, 799], "id": 1139, "text": " "}, {"box": [349, 788, 378, 799], "id": 1140, "text": "b"}, {"box": [349, 788, 378, 799], "id": 1141, "text": "e"}, {"box": [349, 788, 378, 799], "id": 1142, "text": "l"}, {"box": [349, 788, 378, 799], "id": 1143, "text": "o"}, {"box": [349, 788, 378, 799], "id": 1144, "text": "w"}, {"box": [349, 788, 378, 799], "id": 1145, "text": " "}, {"box": [381, 788, 396, 798], "id": 1146, "text": "v"}, {"box": [381, 788, 396, 798], "id": 1147, "text": "i"}, {"box": [381, 788, 396, 798], "id": 1148, "text": "a"}, {"box": [381, 788, 396, 798], "id": 1149, "text": " "}, {"box": [401, 788, 415, 798], "id": 1150, "text": "t"}, {"box": [401, 788, 415, 798], "id": 1151, "text": "h"}, {"box": [401, 788, 415, 798], "id": 1152, "text": "e"}, {"box": [401, 788, 415, 798], "id": 1153, "text": " "}, {"box": [419, 786, 430, 797], "id": 1154, "text": "U"}, {"box": [419, 786, 430, 797], "id": 1155, "text": "."}, {"box": [419, 786, 430, 797], "id": 1156, "text": " "}, {"box": [432, 788, 442, 798], "id": 1157, "text": "S"}, {"box": [432, 788, 442, 798], "id": 1158, "text": "."}, {"box": [432, 788, 442, 798], "id": 1159, "text": " "}, {"box": [446, 788, 475, 799], "id": 1160, "text": "P"}, {"box": [446, 788, 475, 799], "id": 1161, "text": "o"}, {"box": [446, 788, 475, 799], "id": 1162, "text": "s"}, {"box": [446, 788, 475, 799], "id": 1163, "text": "t"}, {"box": [446, 788, 475, 799], "id": 1164, "text": "a"}, {"box": [446, 788, 475, 799], "id": 1165, "text": "l"}, {"box": [446, 788, 475, 799], "id": 1166, "text": " "}, {"box": [478, 788, 516, 798], "id": 1167, "text": "S"}, {"box": [478, 788, 516, 798], "id": 1168, "text": "e"}, {"box": [478, 788, 516, 798], "id": 1169, "text": "r"}, {"box": [478, 788, 516, 798], "id": 1170, "text": "v"}, {"box": [478, 788, 516, 798], "id": 1171, "text": "i"}, {"box": [478, 788, 516, 798], "id": 1172, "text": "c"}, {"box": [478, 788, 516, 798], "id": 1173, "text": "e"}, {"box": [478, 788, 516, 798], "id": 1174, "text": "."}, {"box": [478, 788, 516, 798], "id": 1175, "text": " "}, {"box": [527, 788, 558, 799], "id": 1176, "text": "T"}, {"box": [527, 788, 558, 799], "id": 1177, "text": "h"}, {"box": [527, 788, 558, 799], "id": 1178, "text": "a"}, {"box": [527, 788, 558, 799], "id": 1179, "text": "n"}, {"box": [527, 788, 558, 799], "id": 1180, "text": "k"}, {"box": [527, 788, 558, 799], "id": 1181, "text": " "}, {"box": [560, 789, 580, 800], "id": 1182, "text": "y"}, {"box": [560, 789, 580, 800], "id": 1183, "text": "o"}, {"box": [560, 789, 580, 800], "id": 1184, "text": "u"}, {"box": [560, 789, 580, 800], "id": 1185, "text": " "}, {"box": [584, 788, 598, 799], "id": 1186, "text": "f"}, {"box": [584, 788, 598, 799], "id": 1187, "text": "o"}, {"box": [584, 788, 598, 799], "id": 1188, "text": "r"}, {"box": [584, 788, 598, 799], "id": 1189, "text": " "}, {"box": [602, 789, 624, 800], "id": 1190, "text": "y"}, {"box": [602, 789, 624, 800], "id": 1191, "text": "o"}, {"box": [602, 789, 624, 800], "id": 1192, "text": "u"}, {"box": [602, 789, 624, 800], "id": 1193, "text": "r"}, {"box": [602, 789, 624, 800], "id": 1194, "text": " "}, {"box": [163, 802, 219, 813], "id": 1195, "text": "c"}, {"box": [163, 802, 219, 813], "id": 1196, "text": "o"}, {"box": [163, 802, 219, 813], "id": 1197, "text": "o"}, {"box": [163, 802, 219, 813], "id": 1198, "text": "p"}, {"box": [163, 802, 219, 813], "id": 1199, "text": "e"}, {"box": [163, 802, 219, 813], "id": 1200, "text": "r"}, {"box": [163, 802, 219, 813], "id": 1201, "text": "a"}, {"box": [163, 802, 219, 813], "id": 1202, "text": "t"}, {"box": [163, 802, 219, 813], "id": 1203, "text": "i"}, {"box": [163, 802, 219, 813], "id": 1204, "text": "o"}, {"box": [163, 802, 219, 813], "id": 1205, "text": "n"}, {"box": [163, 802, 219, 813], "id": 1206, "text": "."}]}, {"box": [182, 887, 539, 928], "text": "State Office Tower / 30 East Broad Street/ Columbus, Ohio 43215 -3428 www ag state oh us An Equal Opportunity Employer", "id": 25, "words": [{"box": [182, 887, 209, 902], "id": 1208, "text": "S"}, {"box": [182, 887, 209, 902], "id": 1209, "text": "t"}, {"box": [182, 887, 209, 902], "id": 1210, "text": "a"}, {"box": [182, 887, 209, 902], "id": 1211, "text": "t"}, {"box": [182, 887, 209, 902], "id": 1212, "text": "e"}, {"box": [182, 887, 209, 902], "id": 1213, "text": " "}, {"box": [211, 890, 240, 901], "id": 1214, "text": "O"}, {"box": [211, 890, 240, 901], "id": 1215, "text": "f"}, {"box": [211, 890, 240, 901], "id": 1216, "text": "f"}, {"box": [211, 890, 240, 901], "id": 1217, "text": "i"}, {"box": [211, 890, 240, 901], "id": 1218, "text": "c"}, {"box": [211, 890, 240, 901], "id": 1219, "text": "e"}, {"box": [211, 890, 240, 901], "id": 1220, "text": " "}, {"box": [243, 888, 272, 902], "id": 1221, "text": "T"}, {"box": [243, 888, 272, 902], "id": 1222, "text": "o"}, {"box": [243, 888, 272, 902], "id": 1223, "text": "w"}, {"box": [243, 888, 272, 902], "id": 1224, "text": "e"}, {"box": [243, 888, 272, 902], "id": 1225, "text": "r"}, {"box": [243, 888, 272, 902], "id": 1226, "text": " "}, {"box": [275, 888, 281, 899], "id": 1227, "text": "/"}, {"box": [275, 888, 281, 899], "id": 1228, "text": " "}, {"box": [282, 888, 293, 901], "id": 1229, "text": "3"}, {"box": [282, 888, 293, 901], "id": 1230, "text": "0"}, {"box": [282, 888, 293, 901], "id": 1231, "text": " "}, {"box": [296, 888, 318, 899], "id": 1232, "text": "E"}, {"box": [296, 888, 318, 899], "id": 1233, "text": "a"}, {"box": [296, 888, 318, 899], "id": 1234, "text": "s"}, {"box": [296, 888, 318, 899], "id": 1235, "text": "t"}, {"box": [296, 888, 318, 899], "id": 1236, "text": " "}, {"box": [321, 888, 352, 901], "id": 1237, "text": "B"}, {"box": [321, 888, 352, 901], "id": 1238, "text": "r"}, {"box": [321, 888, 352, 901], "id": 1239, "text": "o"}, {"box": [321, 888, 352, 901], "id": 1240, "text": "a"}, {"box": [321, 888, 352, 901], "id": 1241, "text": "d"}, {"box": [321, 888, 352, 901], "id": 1242, "text": " "}, {"box": [355, 888, 391, 899], "id": 1243, "text": "S"}, {"box": [355, 888, 391, 899], "id": 1244, "text": "t"}, {"box": [355, 888, 391, 899], "id": 1245, "text": "r"}, {"box": [355, 888, 391, 899], "id": 1246, "text": "e"}, {"box": [355, 888, 391, 899], "id": 1247, "text": "e"}, {"box": [355, 888, 391, 899], "id": 1248, "text": "t"}, {"box": [355, 888, 391, 899], "id": 1249, "text": "/"}, {"box": [355, 888, 391, 899], "id": 1250, "text": " "}, {"box": [392, 888, 444, 901], "id": 1251, "text": "C"}, {"box": [392, 888, 444, 901], "id": 1252, "text": "o"}, {"box": [392, 888, 444, 901], "id": 1253, "text": "l"}, {"box": [392, 888, 444, 901], "id": 1254, "text": "u"}, {"box": [392, 888, 444, 901], "id": 1255, "text": "m"}, {"box": [392, 888, 444, 901], "id": 1256, "text": "b"}, {"box": [392, 888, 444, 901], "id": 1257, "text": "u"}, {"box": [392, 888, 444, 901], "id": 1258, "text": "s"}, {"box": [392, 888, 444, 901], "id": 1259, "text": ","}, {"box": [392, 888, 444, 901], "id": 1260, "text": " "}, {"box": [447, 888, 471, 899], "id": 1261, "text": "O"}, {"box": [447, 888, 471, 899], "id": 1262, "text": "h"}, {"box": [447, 888, 471, 899], "id": 1263, "text": "i"}, {"box": [447, 888, 471, 899], "id": 1264, "text": "o"}, {"box": [447, 888, 471, 899], "id": 1265, "text": " "}, {"box": [476, 887, 507, 900], "id": 1266, "text": "4"}, {"box": [476, 887, 507, 900], "id": 1267, "text": "3"}, {"box": [476, 887, 507, 900], "id": 1268, "text": "2"}, {"box": [476, 887, 507, 900], "id": 1269, "text": "1"}, {"box": [476, 887, 507, 900], "id": 1270, "text": "5"}, {"box": [476, 887, 507, 900], "id": 1271, "text": " "}, {"box": [508, 887, 539, 901], "id": 1272, "text": "-"}, {"box": [508, 887, 539, 901], "id": 1273, "text": "3"}, {"box": [508, 887, 539, 901], "id": 1274, "text": "4"}, {"box": [508, 887, 539, 901], "id": 1275, "text": "2"}, {"box": [508, 887, 539, 901], "id": 1276, "text": "8"}, {"box": [508, 887, 539, 901], "id": 1277, "text": " "}, {"box": [310, 902, 338, 913], "id": 1278, "text": "w"}, {"box": [310, 902, 338, 913], "id": 1279, "text": "w"}, {"box": [310, 902, 338, 913], "id": 1280, "text": "w"}, {"box": [310, 902, 338, 913], "id": 1281, "text": " "}, {"box": [339, 902, 352, 915], "id": 1282, "text": "a"}, {"box": [339, 902, 352, 915], "id": 1283, "text": "g"}, {"box": [339, 902, 352, 915], "id": 1284, "text": " "}, {"box": [352, 902, 377, 913], "id": 1285, "text": "s"}, {"box": [352, 902, 377, 913], "id": 1286, "text": "t"}, {"box": [352, 902, 377, 913], "id": 1287, "text": "a"}, {"box": [352, 902, 377, 913], "id": 1288, "text": "t"}, {"box": [352, 902, 377, 913], "id": 1289, "text": "e"}, {"box": [352, 902, 377, 913], "id": 1290, "text": " "}, {"box": [378, 902, 392, 913], "id": 1291, "text": "o"}, {"box": [378, 902, 392, 913], "id": 1292, "text": "h"}, {"box": [378, 902, 392, 913], "id": 1293, "text": " "}, {"box": [394, 904, 408, 912], "id": 1294, "text": "u"}, {"box": [394, 904, 408, 912], "id": 1295, "text": "s"}, {"box": [394, 904, 408, 912], "id": 1296, "text": " "}, {"box": [292, 915, 305, 926], "id": 1297, "text": "A"}, {"box": [292, 915, 305, 926], "id": 1298, "text": "n"}, {"box": [292, 915, 305, 926], "id": 1299, "text": " "}, {"box": [307, 913, 332, 927], "id": 1300, "text": "E"}, {"box": [307, 913, 332, 927], "id": 1301, "text": "q"}, {"box": [307, 913, 332, 927], "id": 1302, "text": "u"}, {"box": [307, 913, 332, 927], "id": 1303, "text": "a"}, {"box": [307, 913, 332, 927], "id": 1304, "text": "l"}, {"box": [307, 913, 332, 927], "id": 1305, "text": " "}, {"box": [335, 915, 387, 928], "id": 1306, "text": "O"}, {"box": [335, 915, 387, 928], "id": 1307, "text": "p"}, {"box": [335, 915, 387, 928], "id": 1308, "text": "p"}, {"box": [335, 915, 387, 928], "id": 1309, "text": "o"}, {"box": [335, 915, 387, 928], "id": 1310, "text": "r"}, {"box": [335, 915, 387, 928], "id": 1311, "text": "t"}, {"box": [335, 915, 387, 928], "id": 1312, "text": "u"}, {"box": [335, 915, 387, 928], "id": 1313, "text": "n"}, {"box": [335, 915, 387, 928], "id": 1314, "text": "i"}, {"box": [335, 915, 387, 928], "id": 1315, "text": "t"}, {"box": [335, 915, 387, 928], "id": 1316, "text": "y"}, {"box": [335, 915, 387, 928], "id": 1317, "text": " "}, {"box": [387, 916, 429, 927], "id": 1318, "text": "E"}, {"box": [387, 916, 429, 927], "id": 1319, "text": "m"}, {"box": [387, 916, 429, 927], "id": 1320, "text": "p"}, {"box": [387, 916, 429, 927], "id": 1321, "text": "l"}, {"box": [387, 916, 429, 927], "id": 1322, "text": "o"}, {"box": [387, 916, 429, 927], "id": 1323, "text": "y"}, {"box": [387, 916, 429, 927], "id": 1324, "text": "e"}, {"box": [387, 916, 429, 927], "id": 1325, "text": "r"}]}, {"box": [292, 941, 426, 954], "text": "Primed an ", "id": 26, "words": [{"box": [292, 941, 306, 954], "id": 1327, "text": "å"}, {"box": [292, 941, 306, 954], "id": 1328, "text": " "}, {"box": [306, 943, 341, 951], "id": 1329, "text": "P"}, {"box": [306, 943, 341, 951], "id": 1330, "text": "r"}, {"box": [306, 943, 341, 951], "id": 1331, "text": "i"}, {"box": [306, 943, 341, 951], "id": 1332, "text": "m"}, {"box": [306, 943, 341, 951], "id": 1333, "text": "e"}, {"box": [306, 943, 341, 951], "id": 1334, "text": "d"}, {"box": [306, 943, 341, 951], "id": 1335, "text": " "}, {"box": [341, 944, 355, 951], "id": 1336, "text": "a"}, {"box": [341, 944, 355, 951], "id": 1337, "text": "n"}, {"box": [341, 944, 355, 951], "id": 1338, "text": " "}, {"box": [355, 943, 398, 951], "id": 1339, "text": "å"}, {"box": [355, 943, 398, 951], "id": 1340, "text": " "}, {"box": [399, 943, 426, 951], "id": 1341, "text": "å"}]}, {"box": [184, 405, 233, 423], "text": "12 /10 /98", "id": 27, "words": [{"box": [184, 406, 198, 420], "id": 1343, "text": "1"}, {"box": [184, 406, 198, 420], "id": 1344, "text": "2"}, {"box": [184, 406, 198, 420], "id": 1345, "text": " "}, {"box": [198, 405, 216, 423], "id": 1346, "text": "/"}, {"box": [198, 405, 216, 423], "id": 1347, "text": "1"}, {"box": [198, 405, 216, 423], "id": 1348, "text": "0"}, {"box": [198, 405, 216, 423], "id": 1349, "text": " "}, {"box": [215, 406, 233, 423], "id": 1350, "text": "/"}, {"box": [215, 406, 233, 423], "id": 1351, "text": "9"}, {"box": [215, 406, 233, 423], "id": 1352, "text": "8"}]}], "uid": "./testing_data/images/82092117.png", "img": {"fname": "./testing_data/images/82092117.png", "height": 1000, "width": 754, "image_url": "82092117.png", "url": "82092117.png", "cls_id": 0}, "label_entities": {"question": {"entity_id": 0, "label": "question", "alias": [], "word_idx": [[2, 3, 4, 5], [6, 7, 8, 9, 10, 11], [14, 15, 16, 17, 18], [19, 20, 21, 22, 23, 24], [198, 199, 200, 201, 202, 203, 204, 205], [237, 238, 239, 240, 241, 242, 243, 244, 245, 246, 247, 248], [249, 250, 251, 252, 253, 254, 255, 256, 257, 258, 259, 260, 261, 262], [279, 280, 281, 282, 283, 284, 285, 286, 287, 288, 289, 290, 291, 292, 293, 294, 295, 296, 297, 298, 299, 300, 301, 302, 303, 304, 305, 306, 307, 308, 309, 310, 311, 312, 313, 314, 315, 316, 317], [361, 362, 363, 364, 365, 366, 367, 368, 369, 370, 371, 372, 373, 374, 375, 376, 377, 378, 379, 380, 381, 382], [383, 384, 385, 386, 387, 388, 389, 390, 391, 392, 393, 394, 395, 396, 397, 398, 399, 400, 401, 402, 403, 404]]}, "answer": {"entity_id": 1, "label": "answer", "alias": [], "word_idx": [[12, 13], [34, 35, 36, 37, 38, 39, 40, 41, 42, 43, 44, 45, 46, 47, 48], [182, 183, 184, 185, 186, 187, 188, 189, 190, 191, 192, 193, 194, 195, 196, 197], [206, 207, 208, 209, 210, 211, 212, 213, 214, 215, 216, 217, 218, 219, 220], [221, 222, 223, 224, 225, 226, 227, 228, 229, 230, 231, 232, 233, 234, 235, 236], [263, 264, 265, 266, 267, 268, 269, 270, 271, 272, 273, 274, 275, 276, 277, 278], [318, 319, 320, 321, 322, 323, 324, 325, 326, 327, 328, 329, 330, 331, 332, 333, 334, 335, 336, 337, 338, 339, 340, 341, 342, 343, 344, 345, 346, 347, 348, 349, 350, 351, 352, 353, 354, 355, 356, 357, 358, 359, 360], [496, 497, 498, 499, 500, 501, 502, 503, 504, 505, 506, 507, 508, 509, 510, 511, 512, 513, 514, 515, 516, 517, 518, 519, 520, 521, 522, 523, 524, 525, 526, 527, 528, 529, 530, 531, 532, 533, 534, 535, 536, 537, 538, 539, 540, 541, 542, 543, 544, 545, 546, 547, 548, 549, 550, 551, 552, 553, 554, 555, 556, 557, 558, 559, 560, 561, 562, 563, 564, 565, 566, 567, 568, 569, 570, 571, 572, 573, 574, 575, 576, 577, 578, 579, 580, 581, 582, 583, 584, 585, 586, 587, 588, 589, 590, 591, 592, 593, 594, 595, 596, 597, 598, 599, 600, 601, 602, 603, 604, 605, 606, 607, 608, 609, 610, 611, 612, 613, 614, 615, 616, 617, 618, 619, 620, 621, 622, 623, 624, 625, 626, 627, 628, 629, 630, 631, 632, 633, 634, 635, 636, 637, 638, 639, 640, 641, 642, 643, 644, 645, 646, 647, 648, 649, 650, 651, 652, 653, 654, 655, 656, 657, 658, 659, 660, 661, 662, 663, 664, 665, 666, 667, 668, 669, 670, 671, 672, 673, 674, 675, 676, 677, 678, 679, 680, 681, 682, 683, 684, 685, 686, 687, 688, 689, 690, 691, 692, 693, 694, 695, 696, 697, 698, 699, 700, 701, 702, 703, 704, 705, 706, 707, 708, 709, 710, 711, 712, 713, 714, 715, 716, 717, 718, 719, 720, 721, 722, 723, 724, 725, 726, 727, 728, 729, 730, 731, 732, 733, 734, 735, 736, 737, 738, 739, 740, 741, 742, 743, 744, 745, 746, 747, 748, 749, 750, 751, 752, 753, 754, 755, 756, 757, 758, 759, 760, 761, 762, 763, 764, 765, 766, 767, 768, 769, 770, 771, 772, 773, 774, 775, 776, 777, 778, 779, 780, 781, 782, 783, 784, 785, 786, 787, 788, 789, 790, 791, 792, 793, 794, 795, 796, 797, 798, 799, 800, 801, 802, 803, 804, 805, 806, 807, 808, 809, 810, 811, 812, 813, 814, 815, 816, 817, 818, 819, 820, 821, 822, 823, 824, 825, 826, 827, 828, 829, 830, 831, 832, 833, 834, 835, 836, 837, 838, 839, 840, 841, 842, 843, 844, 845, 846, 847, 848, 849, 850, 851, 852, 853, 854, 855, 856, 857, 858, 859, 860, 861, 862, 863, 864, 865, 866, 867, 868, 869, 870, 871, 872, 873, 874, 875, 876, 877, 878, 879, 880, 881, 882, 883, 884, 885, 886, 887, 888, 889, 890, 891, 892, 893, 894, 895, 896, 897, 898, 899, 900, 901, 902, 903, 904, 905, 906, 907, 908, 909, 910, 911, 912, 913, 914, 915, 916, 917, 918, 919, 920, 921, 922, 923, 924, 925, 926, 927, 928, 929, 930, 931, 932, 933, 934, 935, 936, 937, 938, 939, 940, 941, 942, 943, 944, 945, 946, 947, 948, 949, 950, 951, 952, 953, 954, 955, 956, 957, 958, 959, 960, 961, 962, 963, 964, 965, 966, 967, 968, 969, 970, 971, 972, 973, 974, 975, 976, 977, 978, 979, 980, 981, 982, 983, 984, 985, 986, 987, 988, 989, 990, 991, 992, 993, 994, 995, 996, 997, 998, 999, 1000, 1001, 1002, 1003, 1004, 1005, 1006, 1007, 1008, 1009, 1010, 1011, 1012, 1013, 1014, 1015, 1016, 1017, 1018, 1019, 1020, 1021, 1022, 1023, 1024, 1025, 1026, 1027, 1028, 1029, 1030, 1031, 1032, 1033, 1034, 1035, 1036, 1037, 1038, 1039, 1040, 1041, 1042, 1043, 1044, 1045, 1046, 1047, 1048, 1049, 1050, 1051, 1052, 1053, 1054, 1055, 1056, 1057, 1058, 1059, 1060, 1061, 1062, 1063, 1064, 1065, 1066, 1067, 1068, 1069, 1070, 1071, 1072, 1073, 1074, 1075, 1076, 1077, 1078, 1079, 1080, 1081, 1082, 1083, 1084, 1085, 1086, 1087, 1088, 1089, 1090, 1091, 1092, 1093, 1094, 1095, 1096, 1097, 1098, 1099, 1100, 1101, 1102, 1103, 1104, 1105, 1106, 1107, 1108, 1109, 1110, 1111, 1112, 1113, 1114, 1115, 1116, 1117, 1118, 1119, 1120, 1121, 1122, 1123, 1124, 1125, 1126, 1127, 1128, 1129, 1130, 1131, 1132, 1133, 1134, 1135, 1136, 1137, 1138, 1139, 1140, 1141, 1142, 1143, 1144, 1145, 1146, 1147, 1148, 1149, 1150, 1151, 1152, 1153, 1154, 1155, 1156, 1157, 1158, 1159, 1160, 1161, 1162, 1163, 1164, 1165, 1166, 1167, 1168, 1169, 1170, 1171, 1172, 1173, 1174, 1175, 1176, 1177, 1178, 1179, 1180, 1181, 1182, 1183, 1184, 1185, 1186, 1187, 1188, 1189, 1190, 1191, 1192, 1193, 1194, 1195, 1196, 1197, 1198, 1199, 1200, 1201, 1202, 1203, 1204, 1205, 1206, 1207], [1343, 1344, 1345, 1346, 1347, 1348, 1349, 1350, 1351, 1352, 1353]]}, "header": {"entity_id": 2, "label": "header", "alias": [], "word_idx": [[97, 98, 99, 100, 101, 102, 103, 104, 105, 106, 107, 108, 109, 110, 111, 112, 113, 114, 115, 116, 117, 118, 119, 120, 121, 122, 123, 124, 125, 126, 127, 128, 129, 130, 131, 132, 133], [134, 135, 136, 137, 138, 139, 140, 141, 142, 143, 144, 145, 146, 147, 148, 149, 150, 151, 152, 153, 154, 155, 156, 157, 158, 159, 160, 161, 162, 163, 164, 165, 166, 167, 168, 169, 170, 171, 172, 173, 174, 175, 176, 177, 178, 179, 180, 181], [405, 406, 407, 408, 409, 410, 411, 412, 413, 414, 415, 416, 417, 418, 419, 420, 421, 422, 423, 424, 425, 426, 427, 428, 429, 430, 431, 432, 433, 434, 435, 436, 437, 438, 439, 440, 441, 442, 443, 444, 445, 446, 447, 448, 449, 450, 451, 452, 453, 454, 455, 456, 457, 458, 459, 460, 461, 462, 463, 464, 465, 466, 467, 468, 469, 470, 471, 472, 473, 474, 475, 476, 477, 478, 479, 480, 481, 482, 483, 484, 485, 486, 487, 488, 489, 490, 491, 492, 493, 494, 495]]}}, "label_linkings": [[1, 14], [2, 27], [19, 3], [4, 7], [5, 24], [13, 12], [16, 15], [17, 18], [21, 20]], "tag": "82092117", "label_groups": [[[2, 3, 4, 5], [206, 207, 208, 209, 210, 211, 212, 213, 214, 215, 216, 217, 218, 219, 220]], [[6, 7, 8, 9, 10, 11], [1343, 1344, 1345, 1346, 1347, 1348, 1349, 1350, 1351, 1352, 1353]], [[279, 280, 281, 282, 283, 284, 285, 286, 287, 288, 289, 290, 291, 292, 293, 294, 295, 296, 297, 298, 299, 300, 301, 302, 303, 304, 305, 306, 307, 308, 309, 310, 311, 312, 313, 314, 315, 316, 317], [12, 13]], [[14, 15, 16, 17, 18], [34, 35, 36, 37, 38, 39, 40, 41, 42, 43, 44, 45, 46, 47, 48]], [[19, 20, 21, 22, 23, 24], [496, 497, 498, 499, 500, 501, 502, 503, 504, 505, 506, 507, 508, 509, 510, 511, 512, 513, 514, 515, 516, 517, 518, 519, 520, 521, 522, 523, 524, 525, 526, 527, 528, 529, 530, 531, 532, 533, 534, 535, 536, 537, 538, 539, 540, 541, 542, 543, 544, 545, 546, 547, 548, 549, 550, 551, 552, 553, 554, 555, 556, 557, 558, 559, 560, 561, 562, 563, 564, 565, 566, 567, 568, 569, 570, 571, 572, 573, 574, 575, 576, 577, 578, 579, 580, 581, 582, 583, 584, 585, 586, 587, 588, 589, 590, 591, 592, 593, 594, 595, 596, 597, 598, 599, 600, 601, 602, 603, 604, 605, 606, 607, 608, 609, 610, 611, 612, 613, 614, 615, 616, 617, 618, 619, 620, 621, 622, 623, 624, 625, 626, 627, 628, 629, 630, 631, 632, 633, 634, 635, 636, 637, 638, 639, 640, 641, 642, 643, 644, 645, 646, 647, 648, 649, 650, 651, 652, 653, 654, 655, 656, 657, 658, 659, 660, 661, 662, 663, 664, 665, 666, 667, 668, 669, 670, 671, 672, 673, 674, 675, 676, 677, 678, 679, 680, 681, 682, 683, 684, 685, 686, 687, 688, 689, 690, 691, 692, 693, 694, 695, 696, 697, 698, 699, 700, 701, 702, 703, 704, 705, 706, 707, 708, 709, 710, 711, 712, 713, 714, 715, 716, 717, 718, 719, 720, 721, 722, 723, 724, 725, 726, 727, 728, 729, 730, 731, 732, 733, 734, 735, 736, 737, 738, 739, 740, 741, 742, 743, 744, 745, 746, 747, 748, 749, 750, 751, 752, 753, 754, 755, 756, 757, 758, 759, 760, 761, 762, 763, 764, 765, 766, 767, 768, 769, 770, 771, 772, 773, 774, 775, 776, 777, 778, 779, 780, 781, 782, 783, 784, 785, 786, 787, 788, 789, 790, 791, 792, 793, 794, 795, 796, 797, 798, 799, 800, 801, 802, 803, 804, 805, 806, 807, 808, 809, 810, 811, 812, 813, 814, 815, 816, 817, 818, 819, 820, 821, 822, 823, 824, 825, 826, 827, 828, 829, 830, 831, 832, 833, 834, 835, 836, 837, 838, 839, 840, 841, 842, 843, 844, 845, 846, 847, 848, 849, 850, 851, 852, 853, 854, 855, 856, 857, 858, 859, 860, 861, 862, 863, 864, 865, 866, 867, 868, 869, 870, 871, 872, 873, 874, 875, 876, 877, 878, 879, 880, 881, 882, 883, 884, 885, 886, 887, 888, 889, 890, 891, 892, 893, 894, 895, 896, 897, 898, 899, 900, 901, 902, 903, 904, 905, 906, 907, 908, 909, 910, 911, 912, 913, 914, 915, 916, 917, 918, 919, 920, 921, 922, 923, 924, 925, 926, 927, 928, 929, 930, 931, 932, 933, 934, 935, 936, 937, 938, 939, 940, 941, 942, 943, 944, 945, 946, 947, 948, 949, 950, 951, 952, 953, 954, 955, 956, 957, 958, 959, 960, 961, 962, 963, 964, 965, 966, 967, 968, 969, 970, 971, 972, 973, 974, 975, 976, 977, 978, 979, 980, 981, 982, 983, 984, 985, 986, 987, 988, 989, 990, 991, 992, 993, 994, 995, 996, 997, 998, 999, 1000, 1001, 1002, 1003, 1004, 1005, 1006, 1007, 1008, 1009, 1010, 1011, 1012, 1013, 1014, 1015, 1016, 1017, 1018, 1019, 1020, 1021, 1022, 1023, 1024, 1025, 1026, 1027, 1028, 1029, 1030, 1031, 1032, 1033, 1034, 1035, 1036, 1037, 1038, 1039, 1040, 1041, 1042, 1043, 1044, 1045, 1046, 1047, 1048, 1049, 1050, 1051, 1052, 1053, 1054, 1055, 1056, 1057, 1058, 1059, 1060, 1061, 1062, 1063, 1064, 1065, 1066, 1067, 1068, 1069, 1070, 1071, 1072, 1073, 1074, 1075, 1076, 1077, 1078, 1079, 1080, 1081, 1082, 1083, 1084, 1085, 1086, 1087, 1088, 1089, 1090, 1091, 1092, 1093, 1094, 1095, 1096, 1097, 1098, 1099, 1100, 1101, 1102, 1103, 1104, 1105, 1106, 1107, 1108, 1109, 1110, 1111, 1112, 1113, 1114, 1115, 1116, 1117, 1118, 1119, 1120, 1121, 1122, 1123, 1124, 1125, 1126, 1127, 1128, 1129, 1130, 1131, 1132, 1133, 1134, 1135, 1136, 1137, 1138, 1139, 1140, 1141, 1142, 1143, 1144, 1145, 1146, 1147, 1148, 1149, 1150, 1151, 1152, 1153, 1154, 1155, 1156, 1157, 1158, 1159, 1160, 1161, 1162, 1163, 1164, 1165, 1166, 1167, 1168, 1169, 1170, 1171, 1172, 1173, 1174, 1175, 1176, 1177, 1178, 1179, 1180, 1181, 1182, 1183, 1184, 1185, 1186, 1187, 1188, 1189, 1190, 1191, 1192, 1193, 1194, 1195, 1196, 1197, 1198, 1199, 1200, 1201, 1202, 1203, 1204, 1205, 1206, 1207]], [[198, 199, 200, 201, 202, 203, 204, 205], [182, 183, 184, 185, 186, 187, 188, 189, 190, 191, 192, 193, 194, 195, 196, 197]], [[237, 238, 239, 240, 241, 242, 243, 244, 245, 246, 247, 248], [221, 222, 223, 224, 225, 226, 227, 228, 229, 230, 231, 232, 233, 234, 235, 236]], [[249, 250, 251, 252, 253, 254, 255, 256, 257, 258, 259, 260, 261, 262], [263, 264, 265, 266, 267, 268, 269, 270, 271, 272, 273, 274, 275, 276, 277, 278]], [[361, 362, 363, 364, 365, 366, 367, 368, 369, 370, 371, 372, 373, 374, 375, 376, 377, 378, 379, 380, 381, 382], [318, 319, 320, 321, 322, 323, 324, 325, 326, 327, 328, 329, 330, 331, 332, 333, 334, 335, 336, 337, 338, 339, 340, 341, 342, 343, 344, 345, 346, 347, 348, 349, 350, 351, 352, 353, 354, 355, 356, 357, 358, 359, 360]]]}