{"document": [{"box": [395, 483, 442, 496], "text": "Address", "id": 0, "words": [{"box": [395, 483, 442, 496], "id": 0, "text": "A"}, {"box": [395, 483, 442, 496], "id": 1, "text": "d"}, {"box": [395, 483, 442, 496], "id": 2, "text": "d"}, {"box": [395, 483, 442, 496], "id": 3, "text": "r"}, {"box": [395, 483, 442, 496], "id": 4, "text": "e"}, {"box": [395, 483, 442, 496], "id": 5, "text": "s"}, {"box": [395, 483, 442, 496], "id": 6, "text": "s"}]}, {"box": [397, 507, 419, 518], "text": "City", "id": 1, "words": [{"box": [397, 507, 419, 518], "id": 8, "text": "C"}, {"box": [397, 507, 419, 518], "id": 9, "text": "i"}, {"box": [397, 507, 419, 518], "id": 10, "text": "t"}, {"box": [397, 507, 419, 518], "id": 11, "text": "y"}]}, {"box": [395, 529, 426, 540], "text": "State", "id": 2, "words": [{"box": [395, 529, 426, 540], "id": 13, "text": "S"}, {"box": [395, 529, 426, 540], "id": 14, "text": "t"}, {"box": [395, 529, 426, 540], "id": 15, "text": "a"}, {"box": [395, 529, 426, 540], "id": 16, "text": "t"}, {"box": [395, 529, 426, 540], "id": 17, "text": "e"}]}, {"box": [658, 528, 676, 542], "text": "Zip", "id": 3, "words": [{"box": [658, 528, 676, 542], "id": 19, "text": "Z"}, {"box": [658, 528, 676, 542], "id": 20, "text": "i"}, {"box": [658, 528, 676, 542], "id": 21, "text": "p"}]}, {"box": [619, 584, 682, 598], "text": "BRAND", "id": 4, "words": [{"box": [619, 584, 682, 598], "id": 23, "text": "B"}, {"box": [619, 584, 682, 598], "id": 24, "text": "R"}, {"box": [619, 584, 682, 598], "id": 25, "text": "A"}, {"box": [619, 584, 682, 598], "id": 26, "text": "N"}, {"box": [619, 584, 682, 598], "id": 27, "text": "D"}]}, {"box": [708, 409, 732, 422], "text": "1982", "id": 5, "words": [{"box": [708, 409, 732, 422], "id": 29, "text": "1"}, {"box": [708, 409, 732, 422], "id": 30, "text": "9"}, {"box": [708, 409, 732, 422], "id": 31, "text": "8"}, {"box": [708, 409, 732, 422], "id": 32, "text": "2"}]}, {"box": [701, 747, 719, 832], "text": "88057519", "id": 6, "words": [{"box": [701, 747, 719, 832], "id": 34, "text": "8"}, {"box": [701, 747, 719, 832], "id": 35, "text": "8"}, {"box": [701, 747, 719, 832], "id": 36, "text": "0"}, {"box": [701, 747, 719, 832], "id": 37, "text": "5"}, {"box": [701, 747, 719, 832], "id": 38, "text": "7"}, {"box": [701, 747, 719, 832], "id": 39, "text": "5"}, {"box": [701, 747, 719, 832], "id": 40, "text": "1"}, {"box": [701, 747, 719, 832], "id": 41, "text": "9"}]}, {"box": [552, 270, 730, 351], "text": "New SATIN 100's", "id": 7, "words": [{"box": [594, 270, 683, 304], "id": 43, "text": "N"}, {"box": [594, 270, 683, 304], "id": 44, "text": "e"}, {"box": [594, 270, 683, 304], "id": 45, "text": "w"}, {"box": [594, 270, 683, 304], "id": 46, "text": " "}, {"box": [552, 306, 675, 351], "id": 47, "text": "S"}, {"box": [552, 306, 675, 351], "id": 48, "text": "A"}, {"box": [552, 306, 675, 351], "id": 49, "text": "T"}, {"box": [552, 306, 675, 351], "id": 50, "text": "I"}, {"box": [552, 306, 675, 351], "id": 51, "text": "N"}, {"box": [552, 306, 675, 351], "id": 52, "text": " "}, {"box": [677, 313, 730, 348], "id": 53, "text": "1"}, {"box": [677, 313, 730, 348], "id": 54, "text": "0"}, {"box": [677, 313, 730, 348], "id": 55, "text": "0"}, {"box": [677, 313, 730, 348], "id": 56, "text": "'"}, {"box": [677, 313, 730, 348], "id": 57, "text": "s"}]}, {"box": [397, 434, 476, 447], "text": "Direct Account", "id": 8, "words": [{"box": [397, 436, 429, 447], "id": 59, "text": "D"}, {"box": [397, 436, 429, 447], "id": 60, "text": "i"}, {"box": [397, 436, 429, 447], "id": 61, "text": "r"}, {"box": [397, 436, 429, 447], "id": 62, "text": "e"}, {"box": [397, 436, 429, 447], "id": 63, "text": "c"}, {"box": [397, 436, 429, 447], "id": 64, "text": "t"}, {"box": [397, 436, 429, 447], "id": 65, "text": " "}, {"box": [429, 434, 476, 447], "id": 66, "text": "A"}, {"box": [429, 434, 476, 447], "id": 67, "text": "c"}, {"box": [429, 434, 476, 447], "id": 68, "text": "c"}, {"box": [429, 434, 476, 447], "id": 69, "text": "o"}, {"box": [429, 434, 476, 447], "id": 70, "text": "u"}, {"box": [429, 434, 476, 447], "id": 71, "text": "n"}, {"box": [429, 434, 476, 447], "id": 72, "text": "t"}]}, {"box": [395, 455, 477, 472], "text": "Please Ship To", "id": 9, "words": [{"box": [395, 458, 436, 472], "id": 74, "text": "P"}, {"box": [395, 458, 436, 472], "id": 75, "text": "l"}, {"box": [395, 458, 436, 472], "id": 76, "text": "e"}, {"box": [395, 458, 436, 472], "id": 77, "text": "a"}, {"box": [395, 458, 436, 472], "id": 78, "text": "s"}, {"box": [395, 458, 436, 472], "id": 79, "text": "e"}, {"box": [395, 458, 436, 472], "id": 80, "text": " "}, {"box": [437, 455, 459, 472], "id": 81, "text": "S"}, {"box": [437, 455, 459, 472], "id": 82, "text": "h"}, {"box": [437, 455, 459, 472], "id": 83, "text": "i"}, {"box": [437, 455, 459, 472], "id": 84, "text": "p"}, {"box": [437, 455, 459, 472], "id": 85, "text": " "}, {"box": [462, 459, 477, 470], "id": 86, "text": "T"}, {"box": [462, 459, 477, 470], "id": 87, "text": "o"}]}, {"box": [394, 554, 469, 568], "text": "Delivery Date", "id": 10, "words": [{"box": [394, 554, 441, 568], "id": 89, "text": "D"}, {"box": [394, 554, 441, 568], "id": 90, "text": "e"}, {"box": [394, 554, 441, 568], "id": 91, "text": "l"}, {"box": [394, 554, 441, 568], "id": 92, "text": "i"}, {"box": [394, 554, 441, 568], "id": 93, "text": "v"}, {"box": [394, 554, 441, 568], "id": 94, "text": "e"}, {"box": [394, 554, 441, 568], "id": 95, "text": "r"}, {"box": [394, 554, 441, 568], "id": 96, "text": "y"}, {"box": [394, 554, 441, 568], "id": 97, "text": " "}, {"box": [441, 556, 469, 567], "id": 98, "text": "D"}, {"box": [441, 556, 469, 567], "id": 99, "text": "a"}, {"box": [441, 556, 469, 567], "id": 100, "text": "t"}, {"box": [441, 556, 469, 567], "id": 101, "text": "e"}]}, {"box": [411, 582, 555, 599], "text": "No. OF CARTONS", "id": 11, "words": [{"box": [411, 584, 439, 599], "id": 103, "text": "N"}, {"box": [411, 584, 439, 599], "id": 104, "text": "o"}, {"box": [411, 584, 439, 599], "id": 105, "text": "."}, {"box": [411, 584, 439, 599], "id": 106, "text": " "}, {"box": [441, 582, 468, 599], "id": 107, "text": "O"}, {"box": [441, 582, 468, 599], "id": 108, "text": "F"}, {"box": [441, 582, 468, 599], "id": 109, "text": " "}, {"box": [468, 584, 555, 599], "id": 110, "text": "C"}, {"box": [468, 584, 555, 599], "id": 111, "text": "A"}, {"box": [468, 584, 555, 599], "id": 112, "text": "R"}, {"box": [468, 584, 555, 599], "id": 113, "text": "T"}, {"box": [468, 584, 555, 599], "id": 114, "text": "O"}, {"box": [468, 584, 555, 599], "id": 115, "text": "N"}, {"box": [468, 584, 555, 599], "id": 116, "text": "S"}]}, {"box": [574, 617, 682, 634], "text": "Satin Filter 100's", "id": 12, "words": [{"box": [574, 619, 612, 634], "id": 118, "text": "S"}, {"box": [574, 619, 612, 634], "id": 119, "text": "a"}, {"box": [574, 619, 612, 634], "id": 120, "text": "t"}, {"box": [574, 619, 612, 634], "id": 121, "text": "i"}, {"box": [574, 619, 612, 634], "id": 122, "text": "n"}, {"box": [574, 619, 612, 634], "id": 123, "text": " "}, {"box": [613, 619, 645, 634], "id": 124, "text": "F"}, {"box": [613, 619, 645, 634], "id": 125, "text": "i"}, {"box": [613, 619, 645, 634], "id": 126, "text": "l"}, {"box": [613, 619, 645, 634], "id": 127, "text": "t"}, {"box": [613, 619, 645, 634], "id": 128, "text": "e"}, {"box": [613, 619, 645, 634], "id": 129, "text": "r"}, {"box": [613, 619, 645, 634], "id": 130, "text": " "}, {"box": [647, 617, 682, 632], "id": 131, "text": "1"}, {"box": [647, 617, 682, 632], "id": 132, "text": "0"}, {"box": [647, 617, 682, 632], "id": 133, "text": "0"}, {"box": [647, 617, 682, 632], "id": 134, "text": "'"}, {"box": [647, 617, 682, 632], "id": 135, "text": "s"}]}, {"box": [574, 652, 703, 670], "text": "Satin Menthol 100's", "id": 13, "words": [{"box": [574, 652, 612, 669], "id": 137, "text": "S"}, {"box": [574, 652, 612, 669], "id": 138, "text": "a"}, {"box": [574, 652, 612, 669], "id": 139, "text": "t"}, {"box": [574, 652, 612, 669], "id": 140, "text": "i"}, {"box": [574, 652, 612, 669], "id": 141, "text": "n"}, {"box": [574, 652, 612, 669], "id": 142, "text": " "}, {"box": [610, 652, 666, 669], "id": 143, "text": "M"}, {"box": [610, 652, 666, 669], "id": 144, "text": "e"}, {"box": [610, 652, 666, 669], "id": 145, "text": "n"}, {"box": [610, 652, 666, 669], "id": 146, "text": "t"}, {"box": [610, 652, 666, 669], "id": 147, "text": "h"}, {"box": [610, 652, 666, 669], "id": 148, "text": "o"}, {"box": [610, 652, 666, 669], "id": 149, "text": "l"}, {"box": [610, 652, 666, 669], "id": 150, "text": " "}, {"box": [669, 652, 703, 670], "id": 151, "text": "1"}, {"box": [669, 652, 703, 670], "id": 152, "text": "0"}, {"box": [669, 652, 703, 670], "id": 153, "text": "0"}, {"box": [669, 652, 703, 670], "id": 154, "text": "'"}, {"box": [669, 652, 703, 670], "id": 155, "text": "s"}]}, {"box": [395, 796, 474, 816], "text": "Signature of Hetail Purchaser", "id": 14, "words": [{"box": [397, 796, 442, 807], "id": 157, "text": "S"}, {"box": [397, 796, 442, 807], "id": 158, "text": "i"}, {"box": [397, 796, 442, 807], "id": 159, "text": "g"}, {"box": [397, 796, 442, 807], "id": 160, "text": "n"}, {"box": [397, 796, 442, 807], "id": 161, "text": "a"}, {"box": [397, 796, 442, 807], "id": 162, "text": "t"}, {"box": [397, 796, 442, 807], "id": 163, "text": "u"}, {"box": [397, 796, 442, 807], "id": 164, "text": "r"}, {"box": [397, 796, 442, 807], "id": 165, "text": "e"}, {"box": [397, 796, 442, 807], "id": 166, "text": " "}, {"box": [441, 796, 455, 806], "id": 167, "text": "o"}, {"box": [441, 796, 455, 806], "id": 168, "text": "f"}, {"box": [441, 796, 455, 806], "id": 169, "text": " "}, {"box": [395, 809, 424, 816], "id": 170, "text": "H"}, {"box": [395, 809, 424, 816], "id": 171, "text": "e"}, {"box": [395, 809, 424, 816], "id": 172, "text": "t"}, {"box": [395, 809, 424, 816], "id": 173, "text": "a"}, {"box": [395, 809, 424, 816], "id": 174, "text": "i"}, {"box": [395, 809, 424, 816], "id": 175, "text": "l"}, {"box": [395, 809, 424, 816], "id": 176, "text": " "}, {"box": [427, 806, 474, 816], "id": 177, "text": "P"}, {"box": [427, 806, 474, 816], "id": 178, "text": "u"}, {"box": [427, 806, 474, 816], "id": 179, "text": "r"}, {"box": [427, 806, 474, 816], "id": 180, "text": "c"}, {"box": [427, 806, 474, 816], "id": 181, "text": "h"}, {"box": [427, 806, 474, 816], "id": 182, "text": "a"}, {"box": [427, 806, 474, 816], "id": 183, "text": "s"}, {"box": [427, 806, 474, 816], "id": 184, "text": "e"}, {"box": [427, 806, 474, 816], "id": 185, "text": "r"}]}, {"box": [398, 830, 493, 852], "text": "Order Taken By Sales Representative", "id": 15, "words": [{"box": [398, 830, 423, 843], "id": 187, "text": "O"}, {"box": [398, 830, 423, 843], "id": 188, "text": "r"}, {"box": [398, 830, 423, 843], "id": 189, "text": "d"}, {"box": [398, 830, 423, 843], "id": 190, "text": "e"}, {"box": [398, 830, 423, 843], "id": 191, "text": "r"}, {"box": [398, 830, 423, 843], "id": 192, "text": " "}, {"box": [427, 830, 455, 841], "id": 193, "text": "T"}, {"box": [427, 830, 455, 841], "id": 194, "text": "a"}, {"box": [427, 830, 455, 841], "id": 195, "text": "k"}, {"box": [427, 830, 455, 841], "id": 196, "text": "e"}, {"box": [427, 830, 455, 841], "id": 197, "text": "n"}, {"box": [427, 830, 455, 841], "id": 198, "text": " "}, {"box": [457, 834, 470, 842], "id": 199, "text": "B"}, {"box": [457, 834, 470, 842], "id": 200, "text": "y"}, {"box": [457, 834, 470, 842], "id": 201, "text": " "}, {"box": [398, 842, 425, 852], "id": 202, "text": "S"}, {"box": [398, 842, 425, 852], "id": 203, "text": "a"}, {"box": [398, 842, 425, 852], "id": 204, "text": "l"}, {"box": [398, 842, 425, 852], "id": 205, "text": "e"}, {"box": [398, 842, 425, 852], "id": 206, "text": "s"}, {"box": [398, 842, 425, 852], "id": 207, "text": " "}, {"box": [425, 842, 493, 852], "id": 208, "text": "R"}, {"box": [425, 842, 493, 852], "id": 209, "text": "e"}, {"box": [425, 842, 493, 852], "id": 210, "text": "p"}, {"box": [425, 842, 493, 852], "id": 211, "text": "r"}, {"box": [425, 842, 493, 852], "id": 212, "text": "e"}, {"box": [425, 842, 493, 852], "id": 213, "text": "s"}, {"box": [425, 842, 493, 852], "id": 214, "text": "e"}, {"box": [425, 842, 493, 852], "id": 215, "text": "n"}, {"box": [425, 842, 493, 852], "id": 216, "text": "t"}, {"box": [425, 842, 493, 852], "id": 217, "text": "a"}, {"box": [425, 842, 493, 852], "id": 218, "text": "t"}, {"box": [425, 842, 493, 852], "id": 219, "text": "i"}, {"box": [425, 842, 493, 852], "id": 220, "text": "v"}, {"box": [425, 842, 493, 852], "id": 221, "text": "e"}]}, {"box": [518, 858, 631, 867], "text": "DIRECT ACCOUNT", "id": 16, "words": [{"box": [518, 859, 565, 867], "id": 223, "text": "D"}, {"box": [518, 859, 565, 867], "id": 224, "text": "I"}, {"box": [518, 859, 565, 867], "id": 225, "text": "R"}, {"box": [518, 859, 565, 867], "id": 226, "text": "E"}, {"box": [518, 859, 565, 867], "id": 227, "text": "C"}, {"box": [518, 859, 565, 867], "id": 228, "text": "T"}, {"box": [518, 859, 565, 867], "id": 229, "text": " "}, {"box": [568, 858, 631, 866], "id": 230, "text": "A"}, {"box": [568, 858, 631, 866], "id": 231, "text": "C"}, {"box": [568, 858, 631, 866], "id": 232, "text": "C"}, {"box": [568, 858, 631, 866], "id": 233, "text": "O"}, {"box": [568, 858, 631, 866], "id": 234, "text": "U"}, {"box": [568, 858, 631, 866], "id": 235, "text": "N"}, {"box": [568, 858, 631, 866], "id": 236, "text": "T"}]}], "uid": "./training_data/images/88057519.png", "img": {"fname": "./training_data/images/88057519.png", "height": 1000, "width": 777, "image_url": "88057519.png", "url": "88057519.png", "cls_id": 0}, "label_entities": {"question": {"entity_id": 0, "label": "question", "alias": [], "word_idx": [[0, 1, 2, 3, 4, 5, 6, 7], [8, 9, 10, 11, 12], [13, 14, 15, 16, 17, 18], [19, 20, 21, 22], [23, 24, 25, 26, 27, 28], [59, 60, 61, 62, 63, 64, 65, 66, 67, 68, 69, 70, 71, 72, 73], [74, 75, 76, 77, 78, 79, 80, 81, 82, 83, 84, 85, 86, 87, 88], [89, 90, 91, 92, 93, 94, 95, 96, 97, 98, 99, 100, 101, 102], [103, 104, 105, 106, 107, 108, 109, 110, 111, 112, 113, 114, 115, 116, 117], [157, 158, 159, 160, 161, 162, 163, 164, 165, 166, 167, 168, 169, 170, 171, 172, 173, 174, 175, 176, 177, 178, 179, 180, 181, 182, 183, 184, 185, 186]]}, "header": {"entity_id": 1, "label": "header", "alias": [], "word_idx": [[43, 44, 45, 46, 47, 48, 49, 50, 51, 52, 53, 54, 55, 56, 57, 58]]}, "answer": {"entity_id": 2, "label": "answer", "alias": [], "word_idx": [[118, 119, 120, 121, 122, 123, 124, 125, 126, 127, 128, 129, 130, 131, 132, 133, 134, 135, 136], [137, 138, 139, 140, 141, 142, 143, 144, 145, 146, 147, 148, 149, 150, 151, 152, 153, 154, 155, 156]]}}, "label_linkings": [[4, 12], [4, 13]], "tag": "88057519", "label_groups": [[[23, 24, 25, 26, 27, 28], [118, 119, 120, 121, 122, 123, 124, 125, 126, 127, 128, 129, 130, 131, 132, 133, 134, 135, 136]], [[23, 24, 25, 26, 27, 28], [137, 138, 139, 140, 141, 142, 143, 144, 145, 146, 147, 148, 149, 150, 151, 152, 153, 154, 155, 156]]]}